[
  {
    "Type": "UserDefinedEnum",
    "Name": "EPhotoModeUploadList",
    "Class": "UScriptClass'UserDefinedEnum'",
    "Properties": {
      "DisplayNameMap": [
        {
          "NewEnumerator0": {
            "Namespace": "",
            "Key": "B2C08C224824299A0150EEBEAA8B5E5C",
            "SourceString": "ThumbnailNone",
            "LocalizedString": "ThumbnailNone"
          }
        },
        {
          "NewEnumerator1": {
            "Namespace": "",
            "Key": "D4E645674069F02B793E24BFE6262112",
            "SourceString": "ThumbnailOn",
            "LocalizedString": "ThumbnailOn"
          }
        },
        {
          "NewEnumerator2": {
            "Namespace": "",
            "Key": "609466D849C79FBFBFAAB59AE0FD14BE",
            "SourceString": "ThumbnailLoading",
            "LocalizedString": "ThumbnailLoading"
          }
        }
      ]
    },
    "Names": {
      "EPhotoModeUploadList::NewEnumerator0": 0,
      "EPhotoModeUploadList::NewEnumerator1": 1,
      "EPhotoModeUploadList::NewEnumerator2": 2,
      "EPhotoModeUploadList::EPhotoModeUploadList_MAX": 3
    },
    "CppForm": "Namespaced"
  }
]