[
  {
    "Type": "DataTable",
    "Name": "DT_WeaponAssetDB_Enemy",
    "Class": "UScriptClass'DataTable'",
    "Properties": {
      "RowStruct": {
        "ObjectName": "ScriptStruct'SBWeaponAssetData'",
        "ObjectPath": "/Script/SkyBlue"
      }
    },
    "Rows": {
      "WE00_01_01": {
        "IsTwinWeapon": false,
        "IsTwinWeaponAssetDiff": false,
        "WeaponAsset1": {
          "WeaponBase": {
            "AssetPathName": "/Game/Blueprints/Weapon/Base/BP_Weapon.BP_Weapon_C",
            "SubPathString": ""
          },
          "Mesh": {
            "AssetPathName": "/Game/Character/Weapon/WE/SK_CH_WE00_01_01/Model/SK_CH_WE00_01_01.SK_CH_WE00_01_01",
            "SubPathString": ""
          },
          "ColorList": {
            "AssetPathName": "None",
            "SubPathString": ""
          },
          "MaterialSetList": [],
          "EnvironmentEffectList": [],
          "UnsheatheEffectList": []
        },
        "WeaponAsset2": {
          "WeaponBase": {
            "AssetPathName": "None",
            "SubPathString": ""
          },
          "Mesh": {
            "AssetPathName": "None",
            "SubPathString": ""
          },
          "ColorList": {
            "AssetPathName": "None",
            "SubPathString": ""
          },
          "MaterialSetList": [],
          "EnvironmentEffectList": [],
          "UnsheatheEffectList": []
        }
      },
      "WE00_01_02": {
        "IsTwinWeapon": false,
        "IsTwinWeaponAssetDiff": false,
        "WeaponAsset1": {
          "WeaponBase": {
            "AssetPathName": "/Game/Blueprints/Weapon/Base/BP_Weapon.BP_Weapon_C",
            "SubPathString": ""
          },
          "Mesh": {
            "AssetPathName": "/Game/Character/Weapon/WE/SK_CH_WE00_01_01/Model/SK_CH_WE00_01_01.SK_CH_WE00_01_01",
            "SubPathString": ""
          },
          "ColorList": {
            "AssetPathName": "None",
            "SubPathString": ""
          },
          "MaterialSetList": [],
          "EnvironmentEffectList": [],
          "UnsheatheEffectList": []
        },
        "WeaponAsset2": {
          "WeaponBase": {
            "AssetPathName": "None",
            "SubPathString": ""
          },
          "Mesh": {
            "AssetPathName": "None",
            "SubPathString": ""
          },
          "ColorList": {
            "AssetPathName": "None",
            "SubPathString": ""
          },
          "MaterialSetList": [],
          "EnvironmentEffectList": [],
          "UnsheatheEffectList": []
        }
      },
      "WE00_01_03": {
        "IsTwinWeapon": false,
        "IsTwinWeaponAssetDiff": false,
        "WeaponAsset1": {
          "WeaponBase": {
            "AssetPathName": "/Game/Blueprints/Weapon/Base/BP_Weapon.BP_Weapon_C",
            "SubPathString": ""
          },
          "Mesh": {
            "AssetPathName": "/Game/Character/Weapon/WE/SK_CH_WE00_01_01/Model/SK_CH_WE00_01_01.SK_CH_WE00_01_01",
            "SubPathString": ""
          },
          "ColorList": {
            "AssetPathName": "None",
            "SubPathString": ""
          },
          "MaterialSetList": [],
          "EnvironmentEffectList": [],
          "UnsheatheEffectList": []
        },
        "WeaponAsset2": {
          "WeaponBase": {
            "AssetPathName": "None",
            "SubPathString": ""
          },
          "Mesh": {
            "AssetPathName": "None",
            "SubPathString": ""
          },
          "ColorList": {
            "AssetPathName": "None",
            "SubPathString": ""
          },
          "MaterialSetList": [],
          "EnvironmentEffectList": [],
          "UnsheatheEffectList": []
        }
      },
      "WE00_01_04": {
        "IsTwinWeapon": false,
        "IsTwinWeaponAssetDiff": false,
        "WeaponAsset1": {
          "WeaponBase": {
            "AssetPathName": "/Game/Blueprints/Weapon/Base/BP_Weapon.BP_Weapon_C",
            "SubPathString": ""
          },
          "Mesh": {
            "AssetPathName": "/Game/Character/Weapon/WE/SK_CH_WE00_01_04/Model/SK_CH_WE00_01_04.SK_CH_WE00_01_04",
            "SubPathString": ""
          },
          "ColorList": {
            "AssetPathName": "None",
            "SubPathString": ""
          },
          "MaterialSetList": [],
          "EnvironmentEffectList": [],
          "UnsheatheEffectList": []
        },
        "WeaponAsset2": {
          "WeaponBase": {
            "AssetPathName": "None",
            "SubPathString": ""
          },
          "Mesh": {
            "AssetPathName": "None",
            "SubPathString": ""
          },
          "ColorList": {
            "AssetPathName": "None",
            "SubPathString": ""
          },
          "MaterialSetList": [],
          "EnvironmentEffectList": [],
          "UnsheatheEffectList": []
        }
      },
      "WE00_01_05": {
        "IsTwinWeapon": false,
        "IsTwinWeaponAssetDiff": false,
        "WeaponAsset1": {
          "WeaponBase": {
            "AssetPathName": "/Game/Blueprints/Weapon/Base/BP_Weapon.BP_Weapon_C",
            "SubPathString": ""
          },
          "Mesh": {
            "AssetPathName": "/Game/Character/Weapon/WE/SK_CH_WE00_01_05/Model/SK_CH_WE00_01_05.SK_CH_WE00_01_05",
            "SubPathString": ""
          },
          "ColorList": {
            "AssetPathName": "None",
            "SubPathString": ""
          },
          "MaterialSetList": [],
          "EnvironmentEffectList": [
            {
              "Type": "EEnvironmentType::Unsheathe",
              "bIsPlay": true,
              "Effect": {
                "Particle": {
                  "AssetPathName": "/Game/Effect/Particle/Enemy/00_ECommon/Weapon/PS_ECMN_WE00_01_05.PS_ECMN_WE00_01_05",
                  "SubPathString": ""
                },
                "NiagaraSystem": {
                  "AssetPathName": "None",
                  "SubPathString": ""
                },
                "EffectActor": {
                  "AssetPathName": "None",
                  "SubPathString": ""
                },
                "EffectActorList": [],
                "Sound": {
                  "AssetPathName": "/Game/WwiseAudio/Events/Enemy/E000_22_MKobold/E000_22_MKobold/Play_MKobold_Weapon_Elec_Loop.Play_MKobold_Weapon_Elec_Loop",
                  "SubPathString": ""
                },
                "SoundParam": {
                  "Event": null,
                  "Switch": [],
                  "AttachName": "None",
                  "AutoDestroy": true,
                  "StopWhenOwnerDestroyed": true,
                  "LOD": "ESBAkEventLOD::LOD_Default",
                  "RTPC": [],
                  "DelayTime": 0.0,
                  "bCanReuseAkComponent": true
                },
                "EndSound": {
                  "AssetPathName": "/Game/WwiseAudio/Events/Enemy/E000_22_MKobold/E000_22_MKobold/Stop_MKobold_Weapon_Elec_Loop.Stop_MKobold_Weapon_Elec_Loop",
                  "SubPathString": ""
                },
                "EndSoundParam": {
                  "Event": null,
                  "Switch": [],
                  "AttachName": "None",
                  "AutoDestroy": true,
                  "StopWhenOwnerDestroyed": true,
                  "LOD": "ESBAkEventLOD::LOD_Default",
                  "RTPC": [],
                  "DelayTime": 0.0,
                  "bCanReuseAkComponent": true
                },
                "EffectTarget": "EffectTarget_WeaponMesh_R",
                "ParticleScale": 1.0,
                "LocationOffset": {
                  "X": 0.0,
                  "Y": -75.0,
                  "Z": 25.0
                },
                "RotationOffset": {
                  "Pitch": 0.0,
                  "Yaw": 0.0,
                  "Roll": 0.0
                },
                "bAttach": true,
                "bAbsoluteRotation": false,
                "bDetachWhenDeactivate": false,
                "bVisibleByHiddenSourceActor": false,
                "AttachPointName": "Center_J",
                "ActorParameterName": "None",
                "bOverrideLightingChannels": false,
                "OverrideLightingChannels": {
                  "bChannel0": true,
                  "bChannel1": false,
                  "bChannel2": false
                },
                "bOverrideElementType": true,
                "ElementType": "ESBAttribute::None",
                "VisibleType": "ESBEffectVisibleType::Battle_Production",
                "EffectType": "ESBEffectType::Default"
              }
            }
          ],
          "UnsheatheEffectList": []
        },
        "WeaponAsset2": {
          "WeaponBase": {
            "AssetPathName": "None",
            "SubPathString": ""
          },
          "Mesh": {
            "AssetPathName": "None",
            "SubPathString": ""
          },
          "ColorList": {
            "AssetPathName": "None",
            "SubPathString": ""
          },
          "MaterialSetList": [],
          "EnvironmentEffectList": [],
          "UnsheatheEffectList": []
        }
      },
      "WE00_01_06": {
        "IsTwinWeapon": false,
        "IsTwinWeaponAssetDiff": false,
        "WeaponAsset1": {
          "WeaponBase": {
            "AssetPathName": "/Game/Blueprints/Weapon/Base/BP_Weapon.BP_Weapon_C",
            "SubPathString": ""
          },
          "Mesh": {
            "AssetPathName": "/Game/Character/Weapon/WE/SK_CH_WE00_01_06/Model/SK_CH_WE00_01_06.SK_CH_WE00_01_06",
            "SubPathString": ""
          },
          "ColorList": {
            "AssetPathName": "None",
            "SubPathString": ""
          },
          "MaterialSetList": [],
          "EnvironmentEffectList": [],
          "UnsheatheEffectList": []
        },
        "WeaponAsset2": {
          "WeaponBase": {
            "AssetPathName": "None",
            "SubPathString": ""
          },
          "Mesh": {
            "AssetPathName": "None",
            "SubPathString": ""
          },
          "ColorList": {
            "AssetPathName": "None",
            "SubPathString": ""
          },
          "MaterialSetList": [],
          "EnvironmentEffectList": [],
          "UnsheatheEffectList": []
        }
      },
      "WE00_01_07": {
        "IsTwinWeapon": false,
        "IsTwinWeaponAssetDiff": false,
        "WeaponAsset1": {
          "WeaponBase": {
            "AssetPathName": "/Game/Blueprints/Weapon/Base/BP_Weapon.BP_Weapon_C",
            "SubPathString": ""
          },
          "Mesh": {
            "AssetPathName": "/Game/Character/Weapon/WE/SK_CH_WE00_01_07/Model/SK_CH_WE00_01_07.SK_CH_WE00_01_07",
            "SubPathString": ""
          },
          "ColorList": {
            "AssetPathName": "None",
            "SubPathString": ""
          },
          "MaterialSetList": [],
          "EnvironmentEffectList": [],
          "UnsheatheEffectList": []
        },
        "WeaponAsset2": {
          "WeaponBase": {
            "AssetPathName": "None",
            "SubPathString": ""
          },
          "Mesh": {
            "AssetPathName": "None",
            "SubPathString": ""
          },
          "ColorList": {
            "AssetPathName": "None",
            "SubPathString": ""
          },
          "MaterialSetList": [],
          "EnvironmentEffectList": [],
          "UnsheatheEffectList": []
        }
      },
      "WE00_02_01": {
        "IsTwinWeapon": false,
        "IsTwinWeaponAssetDiff": false,
        "WeaponAsset1": {
          "WeaponBase": {
            "AssetPathName": "/Game/Blueprints/Weapon/Base/BP_Weapon.BP_Weapon_C",
            "SubPathString": ""
          },
          "Mesh": {
            "AssetPathName": "/Game/Character/Weapon/WE/SK_CH_WE00_02_01/Model/SK_CH_WE00_02_01.SK_CH_WE00_02_01",
            "SubPathString": ""
          },
          "ColorList": {
            "AssetPathName": "None",
            "SubPathString": ""
          },
          "MaterialSetList": [],
          "EnvironmentEffectList": [],
          "UnsheatheEffectList": []
        },
        "WeaponAsset2": {
          "WeaponBase": {
            "AssetPathName": "None",
            "SubPathString": ""
          },
          "Mesh": {
            "AssetPathName": "None",
            "SubPathString": ""
          },
          "ColorList": {
            "AssetPathName": "None",
            "SubPathString": ""
          },
          "MaterialSetList": [],
          "EnvironmentEffectList": [],
          "UnsheatheEffectList": []
        }
      },
      "WE00_02_02": {
        "IsTwinWeapon": false,
        "IsTwinWeaponAssetDiff": false,
        "WeaponAsset1": {
          "WeaponBase": {
            "AssetPathName": "/Game/Blueprints/Weapon/Base/BP_Weapon.BP_Weapon_C",
            "SubPathString": ""
          },
          "Mesh": {
            "AssetPathName": "/Game/Character/Weapon/WE/SK_CH_WE00_02_02/Model/SK_CH_WE00_02_02.SK_CH_WE00_02_02",
            "SubPathString": ""
          },
          "ColorList": {
            "AssetPathName": "None",
            "SubPathString": ""
          },
          "MaterialSetList": [],
          "EnvironmentEffectList": [],
          "UnsheatheEffectList": []
        },
        "WeaponAsset2": {
          "WeaponBase": {
            "AssetPathName": "None",
            "SubPathString": ""
          },
          "Mesh": {
            "AssetPathName": "None",
            "SubPathString": ""
          },
          "ColorList": {
            "AssetPathName": "None",
            "SubPathString": ""
          },
          "MaterialSetList": [],
          "EnvironmentEffectList": [],
          "UnsheatheEffectList": []
        }
      },
      "WE00_02_03": {
        "IsTwinWeapon": false,
        "IsTwinWeaponAssetDiff": false,
        "WeaponAsset1": {
          "WeaponBase": {
            "AssetPathName": "/Game/Blueprints/Weapon/Base/BP_Weapon.BP_Weapon_C",
            "SubPathString": ""
          },
          "Mesh": {
            "AssetPathName": "/Game/Character/Weapon/WE/SK_CH_WE00_02_03/Model/SK_CH_WE00_02_03.SK_CH_WE00_02_03",
            "SubPathString": ""
          },
          "ColorList": {
            "AssetPathName": "None",
            "SubPathString": ""
          },
          "MaterialSetList": [],
          "EnvironmentEffectList": [],
          "UnsheatheEffectList": []
        },
        "WeaponAsset2": {
          "WeaponBase": {
            "AssetPathName": "None",
            "SubPathString": ""
          },
          "Mesh": {
            "AssetPathName": "None",
            "SubPathString": ""
          },
          "ColorList": {
            "AssetPathName": "None",
            "SubPathString": ""
          },
          "MaterialSetList": [],
          "EnvironmentEffectList": [],
          "UnsheatheEffectList": []
        }
      },
      "WE00_02_04": {
        "IsTwinWeapon": false,
        "IsTwinWeaponAssetDiff": false,
        "WeaponAsset1": {
          "WeaponBase": {
            "AssetPathName": "/Game/Blueprints/Weapon/Base/BP_Weapon.BP_Weapon_C",
            "SubPathString": ""
          },
          "Mesh": {
            "AssetPathName": "/Game/Character/Weapon/WE/SK_CH_WE00_02_04/Model/SK_CH_WE00_02_04.SK_CH_WE00_02_04",
            "SubPathString": ""
          },
          "ColorList": {
            "AssetPathName": "None",
            "SubPathString": ""
          },
          "MaterialSetList": [],
          "EnvironmentEffectList": [],
          "UnsheatheEffectList": []
        },
        "WeaponAsset2": {
          "WeaponBase": {
            "AssetPathName": "None",
            "SubPathString": ""
          },
          "Mesh": {
            "AssetPathName": "None",
            "SubPathString": ""
          },
          "ColorList": {
            "AssetPathName": "None",
            "SubPathString": ""
          },
          "MaterialSetList": [],
          "EnvironmentEffectList": [],
          "UnsheatheEffectList": []
        }
      },
      "WE00_02_05": {
        "IsTwinWeapon": false,
        "IsTwinWeaponAssetDiff": false,
        "WeaponAsset1": {
          "WeaponBase": {
            "AssetPathName": "/Game/Blueprints/Weapon/Base/BP_Weapon.BP_Weapon_C",
            "SubPathString": ""
          },
          "Mesh": {
            "AssetPathName": "/Game/Character/Weapon/WE/SK_CH_WE00_02_05/Model/SK_CH_WE00_02_05.SK_CH_WE00_02_05",
            "SubPathString": ""
          },
          "ColorList": {
            "AssetPathName": "None",
            "SubPathString": ""
          },
          "MaterialSetList": [],
          "EnvironmentEffectList": [],
          "UnsheatheEffectList": []
        },
        "WeaponAsset2": {
          "WeaponBase": {
            "AssetPathName": "None",
            "SubPathString": ""
          },
          "Mesh": {
            "AssetPathName": "None",
            "SubPathString": ""
          },
          "ColorList": {
            "AssetPathName": "None",
            "SubPathString": ""
          },
          "MaterialSetList": [],
          "EnvironmentEffectList": [],
          "UnsheatheEffectList": []
        }
      },
      "WE00_02_06": {
        "IsTwinWeapon": false,
        "IsTwinWeaponAssetDiff": false,
        "WeaponAsset1": {
          "WeaponBase": {
            "AssetPathName": "/Game/Blueprints/Weapon/Base/BP_Weapon.BP_Weapon_C",
            "SubPathString": ""
          },
          "Mesh": {
            "AssetPathName": "/Game/Character/Weapon/WE/SK_CH_WE00_02_06/Model/SK_CH_WE00_02_06.SK_CH_WE00_02_06",
            "SubPathString": ""
          },
          "ColorList": {
            "AssetPathName": "None",
            "SubPathString": ""
          },
          "MaterialSetList": [],
          "EnvironmentEffectList": [],
          "UnsheatheEffectList": []
        },
        "WeaponAsset2": {
          "WeaponBase": {
            "AssetPathName": "None",
            "SubPathString": ""
          },
          "Mesh": {
            "AssetPathName": "None",
            "SubPathString": ""
          },
          "ColorList": {
            "AssetPathName": "None",
            "SubPathString": ""
          },
          "MaterialSetList": [],
          "EnvironmentEffectList": [],
          "UnsheatheEffectList": []
        }
      },
      "WE00_02_07": {
        "IsTwinWeapon": false,
        "IsTwinWeaponAssetDiff": false,
        "WeaponAsset1": {
          "WeaponBase": {
            "AssetPathName": "/Game/Blueprints/Weapon/Base/BP_Weapon.BP_Weapon_C",
            "SubPathString": ""
          },
          "Mesh": {
            "AssetPathName": "/Game/Character/Weapon/WE/SK_CH_WE00_02_07/Model/SK_CH_WE00_02_07.SK_CH_WE00_02_07",
            "SubPathString": ""
          },
          "ColorList": {
            "AssetPathName": "None",
            "SubPathString": ""
          },
          "MaterialSetList": [],
          "EnvironmentEffectList": [],
          "UnsheatheEffectList": []
        },
        "WeaponAsset2": {
          "WeaponBase": {
            "AssetPathName": "None",
            "SubPathString": ""
          },
          "Mesh": {
            "AssetPathName": "None",
            "SubPathString": ""
          },
          "ColorList": {
            "AssetPathName": "None",
            "SubPathString": ""
          },
          "MaterialSetList": [],
          "EnvironmentEffectList": [],
          "UnsheatheEffectList": []
        }
      },
      "WE00_02_08": {
        "IsTwinWeapon": false,
        "IsTwinWeaponAssetDiff": false,
        "WeaponAsset1": {
          "WeaponBase": {
            "AssetPathName": "/Game/Blueprints/Weapon/Base/BP_Weapon.BP_Weapon_C",
            "SubPathString": ""
          },
          "Mesh": {
            "AssetPathName": "/Game/Character/Weapon/WE/SK_CH_WE00_02_08/Model/SK_CH_WE00_02_08.SK_CH_WE00_02_08",
            "SubPathString": ""
          },
          "ColorList": {
            "AssetPathName": "None",
            "SubPathString": ""
          },
          "MaterialSetList": [],
          "EnvironmentEffectList": [],
          "UnsheatheEffectList": []
        },
        "WeaponAsset2": {
          "WeaponBase": {
            "AssetPathName": "None",
            "SubPathString": ""
          },
          "Mesh": {
            "AssetPathName": "None",
            "SubPathString": ""
          },
          "ColorList": {
            "AssetPathName": "None",
            "SubPathString": ""
          },
          "MaterialSetList": [],
          "EnvironmentEffectList": [],
          "UnsheatheEffectList": []
        }
      },
      "WE00_02_09": {
        "IsTwinWeapon": false,
        "IsTwinWeaponAssetDiff": false,
        "WeaponAsset1": {
          "WeaponBase": {
            "AssetPathName": "/Game/Blueprints/Weapon/Base/BP_Weapon.BP_Weapon_C",
            "SubPathString": ""
          },
          "Mesh": {
            "AssetPathName": "/Game/Character/Weapon/WE/SK_CH_WE00_02_09/Model/SK_CH_WE00_02_09.SK_CH_WE00_02_09",
            "SubPathString": ""
          },
          "ColorList": {
            "AssetPathName": "None",
            "SubPathString": ""
          },
          "MaterialSetList": [],
          "EnvironmentEffectList": [],
          "UnsheatheEffectList": []
        },
        "WeaponAsset2": {
          "WeaponBase": {
            "AssetPathName": "None",
            "SubPathString": ""
          },
          "Mesh": {
            "AssetPathName": "None",
            "SubPathString": ""
          },
          "ColorList": {
            "AssetPathName": "None",
            "SubPathString": ""
          },
          "MaterialSetList": [],
          "EnvironmentEffectList": [],
          "UnsheatheEffectList": []
        }
      },
      "WE00_03_00": {
        "IsTwinWeapon": false,
        "IsTwinWeaponAssetDiff": false,
        "WeaponAsset1": {
          "WeaponBase": {
            "AssetPathName": "/Game/Blueprints/Weapon/Base/BP_Weapon.BP_Weapon_C",
            "SubPathString": ""
          },
          "Mesh": {
            "AssetPathName": "/Game/Character/Weapon/WE/SK_CH_WE00_03_01/Model/SK_CH_WE00_03_01.SK_CH_WE00_03_01",
            "SubPathString": ""
          },
          "ColorList": {
            "AssetPathName": "None",
            "SubPathString": ""
          },
          "MaterialSetList": [],
          "EnvironmentEffectList": [],
          "UnsheatheEffectList": []
        },
        "WeaponAsset2": {
          "WeaponBase": {
            "AssetPathName": "None",
            "SubPathString": ""
          },
          "Mesh": {
            "AssetPathName": "None",
            "SubPathString": ""
          },
          "ColorList": {
            "AssetPathName": "None",
            "SubPathString": ""
          },
          "MaterialSetList": [],
          "EnvironmentEffectList": [],
          "UnsheatheEffectList": []
        }
      },
      "WE00_03_01": {
        "IsTwinWeapon": false,
        "IsTwinWeaponAssetDiff": false,
        "WeaponAsset1": {
          "WeaponBase": {
            "AssetPathName": "/Game/Blueprints/Weapon/Base/BP_Weapon.BP_Weapon_C",
            "SubPathString": ""
          },
          "Mesh": {
            "AssetPathName": "/Game/Character/Weapon/WE/SK_CH_WE00_03_01/Model/SK_CH_WE00_03_01.SK_CH_WE00_03_01",
            "SubPathString": ""
          },
          "ColorList": {
            "AssetPathName": "None",
            "SubPathString": ""
          },
          "MaterialSetList": [],
          "EnvironmentEffectList": [
            {
              "Type": "EEnvironmentType::Unsheathe",
              "bIsPlay": true,
              "Effect": {
                "Particle": {
                  "AssetPathName": "/Game/Effect/Particle/Enemy/00_ECommon/Weapon/PS_ECMN_WE00_03_01.PS_ECMN_WE00_03_01",
                  "SubPathString": ""
                },
                "NiagaraSystem": {
                  "AssetPathName": "None",
                  "SubPathString": ""
                },
                "EffectActor": {
                  "AssetPathName": "None",
                  "SubPathString": ""
                },
                "EffectActorList": [],
                "Sound": {
                  "AssetPathName": "/Game/WwiseAudio/Events/Default_Work_Unit/Play_WE00_03_01_Elec_LOOP.Play_WE00_03_01_Elec_LOOP",
                  "SubPathString": ""
                },
                "SoundParam": {
                  "Event": null,
                  "Switch": [],
                  "AttachName": "None",
                  "AutoDestroy": true,
                  "StopWhenOwnerDestroyed": true,
                  "LOD": "ESBAkEventLOD::LOD_Default",
                  "RTPC": [],
                  "DelayTime": 0.0,
                  "bCanReuseAkComponent": true
                },
                "EndSound": {
                  "AssetPathName": "/Game/WwiseAudio/Events/Default_Work_Unit/Stop_WE00_03_01_Elec_LOOP.Stop_WE00_03_01_Elec_LOOP",
                  "SubPathString": ""
                },
                "EndSoundParam": {
                  "Event": null,
                  "Switch": [],
                  "AttachName": "None",
                  "AutoDestroy": true,
                  "StopWhenOwnerDestroyed": true,
                  "LOD": "ESBAkEventLOD::LOD_Default",
                  "RTPC": [],
                  "DelayTime": 0.0,
                  "bCanReuseAkComponent": true
                },
                "EffectTarget": "EffectTarget_Inventory_0",
                "ParticleScale": 1.0,
                "LocationOffset": {
                  "X": 0.0,
                  "Y": 0.0,
                  "Z": 0.0
                },
                "RotationOffset": {
                  "Pitch": 0.0,
                  "Yaw": 0.0,
                  "Roll": 0.0
                },
                "bAttach": true,
                "bAbsoluteRotation": false,
                "bDetachWhenDeactivate": false,
                "bVisibleByHiddenSourceActor": false,
                "AttachPointName": "R_EdgeBottom",
                "ActorParameterName": "None",
                "bOverrideLightingChannels": false,
                "OverrideLightingChannels": {
                  "bChannel0": true,
                  "bChannel1": false,
                  "bChannel2": false
                },
                "bOverrideElementType": false,
                "ElementType": "ESBAttribute::None",
                "VisibleType": "ESBEffectVisibleType::Battle_Production",
                "EffectType": "ESBEffectType::Default"
              }
            }
          ],
          "UnsheatheEffectList": []
        },
        "WeaponAsset2": {
          "WeaponBase": {
            "AssetPathName": "None",
            "SubPathString": ""
          },
          "Mesh": {
            "AssetPathName": "None",
            "SubPathString": ""
          },
          "ColorList": {
            "AssetPathName": "None",
            "SubPathString": ""
          },
          "MaterialSetList": [],
          "EnvironmentEffectList": [],
          "UnsheatheEffectList": []
        }
      },
      "WE00_04_01": {
        "IsTwinWeapon": false,
        "IsTwinWeaponAssetDiff": false,
        "WeaponAsset1": {
          "WeaponBase": {
            "AssetPathName": "/Game/Blueprints/Weapon/Base/BP_Weapon.BP_Weapon_C",
            "SubPathString": ""
          },
          "Mesh": {
            "AssetPathName": "/Game/Character/Weapon/WE/SK_CH_WE00_04_01/Model/SK_CH_WE00_04_01.SK_CH_WE00_04_01",
            "SubPathString": ""
          },
          "ColorList": {
            "AssetPathName": "None",
            "SubPathString": ""
          },
          "MaterialSetList": [],
          "EnvironmentEffectList": [],
          "UnsheatheEffectList": []
        },
        "WeaponAsset2": {
          "WeaponBase": {
            "AssetPathName": "None",
            "SubPathString": ""
          },
          "Mesh": {
            "AssetPathName": "None",
            "SubPathString": ""
          },
          "ColorList": {
            "AssetPathName": "None",
            "SubPathString": ""
          },
          "MaterialSetList": [],
          "EnvironmentEffectList": [],
          "UnsheatheEffectList": []
        }
      },
      "WE00_04_02": {
        "IsTwinWeapon": false,
        "IsTwinWeaponAssetDiff": false,
        "WeaponAsset1": {
          "WeaponBase": {
            "AssetPathName": "/Game/Blueprints/Weapon/Base/BP_Weapon.BP_Weapon_C",
            "SubPathString": ""
          },
          "Mesh": {
            "AssetPathName": "/Game/Character/Weapon/WE/SK_CH_WE00_04_02/Model/SK_CH_WE00_04_02.SK_CH_WE00_04_02",
            "SubPathString": ""
          },
          "ColorList": {
            "AssetPathName": "None",
            "SubPathString": ""
          },
          "MaterialSetList": [],
          "EnvironmentEffectList": [],
          "UnsheatheEffectList": []
        },
        "WeaponAsset2": {
          "WeaponBase": {
            "AssetPathName": "None",
            "SubPathString": ""
          },
          "Mesh": {
            "AssetPathName": "None",
            "SubPathString": ""
          },
          "ColorList": {
            "AssetPathName": "None",
            "SubPathString": ""
          },
          "MaterialSetList": [],
          "EnvironmentEffectList": [],
          "UnsheatheEffectList": []
        }
      },
      "WE00_04_03": {
        "IsTwinWeapon": false,
        "IsTwinWeaponAssetDiff": false,
        "WeaponAsset1": {
          "WeaponBase": {
            "AssetPathName": "/Game/Blueprints/Weapon/Base/BP_Weapon.BP_Weapon_C",
            "SubPathString": ""
          },
          "Mesh": {
            "AssetPathName": "/Game/Character/Weapon/WE/SK_CH_WE00_04_03/Model/SK_CH_WE00_04_03.SK_CH_WE00_04_03",
            "SubPathString": ""
          },
          "ColorList": {
            "AssetPathName": "None",
            "SubPathString": ""
          },
          "MaterialSetList": [],
          "EnvironmentEffectList": [],
          "UnsheatheEffectList": []
        },
        "WeaponAsset2": {
          "WeaponBase": {
            "AssetPathName": "None",
            "SubPathString": ""
          },
          "Mesh": {
            "AssetPathName": "None",
            "SubPathString": ""
          },
          "ColorList": {
            "AssetPathName": "None",
            "SubPathString": ""
          },
          "MaterialSetList": [],
          "EnvironmentEffectList": [],
          "UnsheatheEffectList": []
        }
      },
      "WE00_04_04": {
        "IsTwinWeapon": false,
        "IsTwinWeaponAssetDiff": false,
        "WeaponAsset1": {
          "WeaponBase": {
            "AssetPathName": "/Game/Blueprints/Weapon/Base/BP_Weapon.BP_Weapon_C",
            "SubPathString": ""
          },
          "Mesh": {
            "AssetPathName": "/Game/Character/Weapon/WE/SK_CH_WE00_04_04/Model/SK_CH_WE00_04_04.SK_CH_WE00_04_04",
            "SubPathString": ""
          },
          "ColorList": {
            "AssetPathName": "None",
            "SubPathString": ""
          },
          "MaterialSetList": [],
          "EnvironmentEffectList": [],
          "UnsheatheEffectList": []
        },
        "WeaponAsset2": {
          "WeaponBase": {
            "AssetPathName": "None",
            "SubPathString": ""
          },
          "Mesh": {
            "AssetPathName": "None",
            "SubPathString": ""
          },
          "ColorList": {
            "AssetPathName": "None",
            "SubPathString": ""
          },
          "MaterialSetList": [],
          "EnvironmentEffectList": [],
          "UnsheatheEffectList": []
        }
      },
      "WE00_04_05": {
        "IsTwinWeapon": false,
        "IsTwinWeaponAssetDiff": false,
        "WeaponAsset1": {
          "WeaponBase": {
            "AssetPathName": "/Game/Blueprints/Weapon/Base/BP_Weapon.BP_Weapon_C",
            "SubPathString": ""
          },
          "Mesh": {
            "AssetPathName": "/Game/Character/Weapon/WE/SK_CH_WE00_04_05/Model/SK_CH_WE00_04_05.SK_CH_WE00_04_05",
            "SubPathString": ""
          },
          "ColorList": {
            "AssetPathName": "None",
            "SubPathString": ""
          },
          "MaterialSetList": [],
          "EnvironmentEffectList": [],
          "UnsheatheEffectList": []
        },
        "WeaponAsset2": {
          "WeaponBase": {
            "AssetPathName": "None",
            "SubPathString": ""
          },
          "Mesh": {
            "AssetPathName": "None",
            "SubPathString": ""
          },
          "ColorList": {
            "AssetPathName": "None",
            "SubPathString": ""
          },
          "MaterialSetList": [],
          "EnvironmentEffectList": [],
          "UnsheatheEffectList": []
        }
      },
      "WE00_04_06": {
        "IsTwinWeapon": false,
        "IsTwinWeaponAssetDiff": false,
        "WeaponAsset1": {
          "WeaponBase": {
            "AssetPathName": "/Game/Blueprints/Weapon/Base/BP_Weapon.BP_Weapon_C",
            "SubPathString": ""
          },
          "Mesh": {
            "AssetPathName": "/Game/Character/Weapon/WE/SK_CH_WE00_04_06/Model/SK_CH_WE00_04_06.SK_CH_WE00_04_06",
            "SubPathString": ""
          },
          "ColorList": {
            "AssetPathName": "None",
            "SubPathString": ""
          },
          "MaterialSetList": [],
          "EnvironmentEffectList": [],
          "UnsheatheEffectList": []
        },
        "WeaponAsset2": {
          "WeaponBase": {
            "AssetPathName": "None",
            "SubPathString": ""
          },
          "Mesh": {
            "AssetPathName": "None",
            "SubPathString": ""
          },
          "ColorList": {
            "AssetPathName": "None",
            "SubPathString": ""
          },
          "MaterialSetList": [],
          "EnvironmentEffectList": [],
          "UnsheatheEffectList": []
        }
      },
      "WE00_04_07": {
        "IsTwinWeapon": false,
        "IsTwinWeaponAssetDiff": false,
        "WeaponAsset1": {
          "WeaponBase": {
            "AssetPathName": "/Game/Blueprints/Weapon/Base/BP_Weapon.BP_Weapon_C",
            "SubPathString": ""
          },
          "Mesh": {
            "AssetPathName": "/Game/Character/Weapon/WE/SK_CH_WE00_04_07/Model/SK_CH_WE00_04_07.SK_CH_WE00_04_07",
            "SubPathString": ""
          },
          "ColorList": {
            "AssetPathName": "None",
            "SubPathString": ""
          },
          "MaterialSetList": [],
          "EnvironmentEffectList": [],
          "UnsheatheEffectList": []
        },
        "WeaponAsset2": {
          "WeaponBase": {
            "AssetPathName": "None",
            "SubPathString": ""
          },
          "Mesh": {
            "AssetPathName": "None",
            "SubPathString": ""
          },
          "ColorList": {
            "AssetPathName": "None",
            "SubPathString": ""
          },
          "MaterialSetList": [],
          "EnvironmentEffectList": [],
          "UnsheatheEffectList": []
        }
      },
      "WE00_08_01": {
        "IsTwinWeapon": false,
        "IsTwinWeaponAssetDiff": false,
        "WeaponAsset1": {
          "WeaponBase": {
            "AssetPathName": "/Game/Blueprints/Weapon/Base/BP_Weapon.BP_Weapon_C",
            "SubPathString": ""
          },
          "Mesh": {
            "AssetPathName": "/Game/Character/Weapon/WE/SK_CH_WE00_08_01/Model/SK_CH_WE00_08_01.SK_CH_WE00_08_01",
            "SubPathString": ""
          },
          "ColorList": {
            "AssetPathName": "None",
            "SubPathString": ""
          },
          "MaterialSetList": [],
          "EnvironmentEffectList": [],
          "UnsheatheEffectList": []
        },
        "WeaponAsset2": {
          "WeaponBase": {
            "AssetPathName": "None",
            "SubPathString": ""
          },
          "Mesh": {
            "AssetPathName": "None",
            "SubPathString": ""
          },
          "ColorList": {
            "AssetPathName": "None",
            "SubPathString": ""
          },
          "MaterialSetList": [],
          "EnvironmentEffectList": [],
          "UnsheatheEffectList": []
        }
      },
      "WE01_01_01": {
        "IsTwinWeapon": false,
        "IsTwinWeaponAssetDiff": false,
        "WeaponAsset1": {
          "WeaponBase": {
            "AssetPathName": "/Game/Blueprints/Weapon/Base/BP_Weapon.BP_Weapon_C",
            "SubPathString": ""
          },
          "Mesh": {
            "AssetPathName": "/Game/Character/Weapon/WE/SK_CH_WE01_01_01/Model/SK_CH_WE01_01_01.SK_CH_WE01_01_01",
            "SubPathString": ""
          },
          "ColorList": {
            "AssetPathName": "None",
            "SubPathString": ""
          },
          "MaterialSetList": [],
          "EnvironmentEffectList": [],
          "UnsheatheEffectList": []
        },
        "WeaponAsset2": {
          "WeaponBase": {
            "AssetPathName": "None",
            "SubPathString": ""
          },
          "Mesh": {
            "AssetPathName": "None",
            "SubPathString": ""
          },
          "ColorList": {
            "AssetPathName": "None",
            "SubPathString": ""
          },
          "MaterialSetList": [],
          "EnvironmentEffectList": [],
          "UnsheatheEffectList": []
        }
      },
      "WE01_01_02": {
        "IsTwinWeapon": false,
        "IsTwinWeaponAssetDiff": false,
        "WeaponAsset1": {
          "WeaponBase": {
            "AssetPathName": "/Game/Blueprints/Weapon/Base/BP_Weapon.BP_Weapon_C",
            "SubPathString": ""
          },
          "Mesh": {
            "AssetPathName": "/Game/Character/Weapon/WE/SK_CH_WE01_01_02/Model/SK_CH_WE01_01_02.SK_CH_WE01_01_02",
            "SubPathString": ""
          },
          "ColorList": {
            "AssetPathName": "None",
            "SubPathString": ""
          },
          "MaterialSetList": [],
          "EnvironmentEffectList": [],
          "UnsheatheEffectList": []
        },
        "WeaponAsset2": {
          "WeaponBase": {
            "AssetPathName": "None",
            "SubPathString": ""
          },
          "Mesh": {
            "AssetPathName": "None",
            "SubPathString": ""
          },
          "ColorList": {
            "AssetPathName": "None",
            "SubPathString": ""
          },
          "MaterialSetList": [],
          "EnvironmentEffectList": [],
          "UnsheatheEffectList": []
        }
      },
      "WE01_01_03": {
        "IsTwinWeapon": false,
        "IsTwinWeaponAssetDiff": false,
        "WeaponAsset1": {
          "WeaponBase": {
            "AssetPathName": "/Game/Blueprints/Weapon/Base/BP_Weapon.BP_Weapon_C",
            "SubPathString": ""
          },
          "Mesh": {
            "AssetPathName": "/Game/Character/Weapon/WE/SK_CH_WE01_01_03/Model/SK_CH_WE01_01_03.SK_CH_WE01_01_03",
            "SubPathString": ""
          },
          "ColorList": {
            "AssetPathName": "None",
            "SubPathString": ""
          },
          "MaterialSetList": [],
          "EnvironmentEffectList": [],
          "UnsheatheEffectList": []
        },
        "WeaponAsset2": {
          "WeaponBase": {
            "AssetPathName": "None",
            "SubPathString": ""
          },
          "Mesh": {
            "AssetPathName": "None",
            "SubPathString": ""
          },
          "ColorList": {
            "AssetPathName": "None",
            "SubPathString": ""
          },
          "MaterialSetList": [],
          "EnvironmentEffectList": [],
          "UnsheatheEffectList": []
        }
      },
      "WE01_01_04": {
        "IsTwinWeapon": false,
        "IsTwinWeaponAssetDiff": false,
        "WeaponAsset1": {
          "WeaponBase": {
            "AssetPathName": "/Game/Blueprints/Weapon/Base/BP_Weapon.BP_Weapon_C",
            "SubPathString": ""
          },
          "Mesh": {
            "AssetPathName": "/Game/Character/Weapon/WE/SK_CH_WE01_01_04/Model/SK_CH_WE01_01_04.SK_CH_WE01_01_04",
            "SubPathString": ""
          },
          "ColorList": {
            "AssetPathName": "None",
            "SubPathString": ""
          },
          "MaterialSetList": [],
          "EnvironmentEffectList": [],
          "UnsheatheEffectList": []
        },
        "WeaponAsset2": {
          "WeaponBase": {
            "AssetPathName": "None",
            "SubPathString": ""
          },
          "Mesh": {
            "AssetPathName": "None",
            "SubPathString": ""
          },
          "ColorList": {
            "AssetPathName": "None",
            "SubPathString": ""
          },
          "MaterialSetList": [],
          "EnvironmentEffectList": [],
          "UnsheatheEffectList": []
        }
      },
      "WE01_04_01": {
        "IsTwinWeapon": false,
        "IsTwinWeaponAssetDiff": false,
        "WeaponAsset1": {
          "WeaponBase": {
            "AssetPathName": "/Game/Blueprints/Weapon/Base/BP_Weapon.BP_Weapon_C",
            "SubPathString": ""
          },
          "Mesh": {
            "AssetPathName": "/Game/Character/Weapon/WE/SK_CH_WE01_04_01/Model/SK_CH_WE01_04_01.SK_CH_WE01_04_01",
            "SubPathString": ""
          },
          "ColorList": {
            "AssetPathName": "None",
            "SubPathString": ""
          },
          "MaterialSetList": [],
          "EnvironmentEffectList": [],
          "UnsheatheEffectList": []
        },
        "WeaponAsset2": {
          "WeaponBase": {
            "AssetPathName": "None",
            "SubPathString": ""
          },
          "Mesh": {
            "AssetPathName": "None",
            "SubPathString": ""
          },
          "ColorList": {
            "AssetPathName": "None",
            "SubPathString": ""
          },
          "MaterialSetList": [],
          "EnvironmentEffectList": [],
          "UnsheatheEffectList": []
        }
      },
      "WE01_04_02": {
        "IsTwinWeapon": false,
        "IsTwinWeaponAssetDiff": false,
        "WeaponAsset1": {
          "WeaponBase": {
            "AssetPathName": "/Game/Blueprints/Weapon/Base/BP_Weapon.BP_Weapon_C",
            "SubPathString": ""
          },
          "Mesh": {
            "AssetPathName": "/Game/Character/Weapon/WE/SK_CH_WE01_04_02/Model/SK_CH_WE01_04_02.SK_CH_WE01_04_02",
            "SubPathString": ""
          },
          "ColorList": {
            "AssetPathName": "None",
            "SubPathString": ""
          },
          "MaterialSetList": [],
          "EnvironmentEffectList": [],
          "UnsheatheEffectList": []
        },
        "WeaponAsset2": {
          "WeaponBase": {
            "AssetPathName": "None",
            "SubPathString": ""
          },
          "Mesh": {
            "AssetPathName": "None",
            "SubPathString": ""
          },
          "ColorList": {
            "AssetPathName": "None",
            "SubPathString": ""
          },
          "MaterialSetList": [],
          "EnvironmentEffectList": [],
          "UnsheatheEffectList": []
        }
      },
      "WE01_05_01": {
        "IsTwinWeapon": false,
        "IsTwinWeaponAssetDiff": false,
        "WeaponAsset1": {
          "WeaponBase": {
            "AssetPathName": "/Game/Blueprints/Weapon/Base/BP_Weapon.BP_Weapon_C",
            "SubPathString": ""
          },
          "Mesh": {
            "AssetPathName": "/Game/Character/Weapon/WE/SK_CH_WE01_05_01/Model/SK_CH_WE01_05_01.SK_CH_WE01_05_01",
            "SubPathString": ""
          },
          "ColorList": {
            "AssetPathName": "None",
            "SubPathString": ""
          },
          "MaterialSetList": [],
          "EnvironmentEffectList": [],
          "UnsheatheEffectList": []
        },
        "WeaponAsset2": {
          "WeaponBase": {
            "AssetPathName": "None",
            "SubPathString": ""
          },
          "Mesh": {
            "AssetPathName": "None",
            "SubPathString": ""
          },
          "ColorList": {
            "AssetPathName": "None",
            "SubPathString": ""
          },
          "MaterialSetList": [],
          "EnvironmentEffectList": [],
          "UnsheatheEffectList": []
        }
      },
      "WE01_06_01": {
        "IsTwinWeapon": false,
        "IsTwinWeaponAssetDiff": false,
        "WeaponAsset1": {
          "WeaponBase": {
            "AssetPathName": "/Game/Blueprints/Weapon/Base/BP_Weapon.BP_Weapon_C",
            "SubPathString": ""
          },
          "Mesh": {
            "AssetPathName": "/Game/Character/Weapon/WE/SK_CH_WE01_06_01/Model/SK_CH_WE01_06_01.SK_CH_WE01_06_01",
            "SubPathString": ""
          },
          "ColorList": {
            "AssetPathName": "None",
            "SubPathString": ""
          },
          "MaterialSetList": [],
          "EnvironmentEffectList": [],
          "UnsheatheEffectList": []
        },
        "WeaponAsset2": {
          "WeaponBase": {
            "AssetPathName": "None",
            "SubPathString": ""
          },
          "Mesh": {
            "AssetPathName": "None",
            "SubPathString": ""
          },
          "ColorList": {
            "AssetPathName": "None",
            "SubPathString": ""
          },
          "MaterialSetList": [],
          "EnvironmentEffectList": [],
          "UnsheatheEffectList": []
        }
      },
      "WE01_07_01": {
        "IsTwinWeapon": false,
        "IsTwinWeaponAssetDiff": false,
        "WeaponAsset1": {
          "WeaponBase": {
            "AssetPathName": "/Game/Blueprints/Weapon/Base/BP_Weapon.BP_Weapon_C",
            "SubPathString": ""
          },
          "Mesh": {
            "AssetPathName": "/Game/Character/Weapon/WE/SK_CH_WE01_07_01/Model/SK_CH_WE01_07_01.SK_CH_WE01_07_01",
            "SubPathString": ""
          },
          "ColorList": {
            "AssetPathName": "None",
            "SubPathString": ""
          },
          "MaterialSetList": [],
          "EnvironmentEffectList": [],
          "UnsheatheEffectList": []
        },
        "WeaponAsset2": {
          "WeaponBase": {
            "AssetPathName": "None",
            "SubPathString": ""
          },
          "Mesh": {
            "AssetPathName": "None",
            "SubPathString": ""
          },
          "ColorList": {
            "AssetPathName": "None",
            "SubPathString": ""
          },
          "MaterialSetList": [],
          "EnvironmentEffectList": [],
          "UnsheatheEffectList": []
        }
      },
      "WE02_01_01": {
        "IsTwinWeapon": false,
        "IsTwinWeaponAssetDiff": false,
        "WeaponAsset1": {
          "WeaponBase": {
            "AssetPathName": "/Game/Blueprints/Weapon/Base/BP_Weapon.BP_Weapon_C",
            "SubPathString": ""
          },
          "Mesh": {
            "AssetPathName": "/Game/Character/Weapon/WE/SK_CH_WE02_01_01/Model/SK_CH_WE02_01_01.SK_CH_WE02_01_01",
            "SubPathString": ""
          },
          "ColorList": {
            "AssetPathName": "None",
            "SubPathString": ""
          },
          "MaterialSetList": [],
          "EnvironmentEffectList": [],
          "UnsheatheEffectList": []
        },
        "WeaponAsset2": {
          "WeaponBase": {
            "AssetPathName": "None",
            "SubPathString": ""
          },
          "Mesh": {
            "AssetPathName": "None",
            "SubPathString": ""
          },
          "ColorList": {
            "AssetPathName": "None",
            "SubPathString": ""
          },
          "MaterialSetList": [],
          "EnvironmentEffectList": [],
          "UnsheatheEffectList": []
        }
      },
      "WE02_01_02": {
        "IsTwinWeapon": false,
        "IsTwinWeaponAssetDiff": false,
        "WeaponAsset1": {
          "WeaponBase": {
            "AssetPathName": "/Game/Blueprints/Weapon/Base/BP_Weapon.BP_Weapon_C",
            "SubPathString": ""
          },
          "Mesh": {
            "AssetPathName": "/Game/Character/Weapon/WE/SK_CH_WE02_01_02/Model/SK_CH_WE02_01_02.SK_CH_WE02_01_02",
            "SubPathString": ""
          },
          "ColorList": {
            "AssetPathName": "None",
            "SubPathString": ""
          },
          "MaterialSetList": [],
          "EnvironmentEffectList": [],
          "UnsheatheEffectList": []
        },
        "WeaponAsset2": {
          "WeaponBase": {
            "AssetPathName": "None",
            "SubPathString": ""
          },
          "Mesh": {
            "AssetPathName": "None",
            "SubPathString": ""
          },
          "ColorList": {
            "AssetPathName": "None",
            "SubPathString": ""
          },
          "MaterialSetList": [],
          "EnvironmentEffectList": [],
          "UnsheatheEffectList": []
        }
      },
      "WE02_01_04": {
        "IsTwinWeapon": false,
        "IsTwinWeaponAssetDiff": false,
        "WeaponAsset1": {
          "WeaponBase": {
            "AssetPathName": "/Game/Blueprints/Weapon/Base/BP_Weapon.BP_Weapon_C",
            "SubPathString": ""
          },
          "Mesh": {
            "AssetPathName": "/Game/Character/Weapon/WE/SK_CH_WE02_01_01/Model/SK_CH_WE02_01_01.SK_CH_WE02_01_01",
            "SubPathString": ""
          },
          "ColorList": {
            "AssetPathName": "None",
            "SubPathString": ""
          },
          "MaterialSetList": [],
          "EnvironmentEffectList": [
            {
              "Type": "EEnvironmentType::Always",
              "bIsPlay": true,
              "Effect": {
                "Particle": {
                  "AssetPathName": "/Game/Effect/Particle/Enemy/00_ECommon/Weapon/PS_E001_Weapon_Fire.PS_E001_Weapon_Fire",
                  "SubPathString": ""
                },
                "NiagaraSystem": {
                  "AssetPathName": "None",
                  "SubPathString": ""
                },
                "EffectActor": {
                  "AssetPathName": "None",
                  "SubPathString": ""
                },
                "EffectActorList": [],
                "Sound": {
                  "AssetPathName": "/Game/WwiseAudio/Events/Default_Work_Unit/Play_Elem_Fire_LOOP_E001_Weapon_Fire.Play_Elem_Fire_LOOP_E001_Weapon_Fire",
                  "SubPathString": ""
                },
                "SoundParam": {
                  "Event": null,
                  "Switch": [],
                  "AttachName": "None",
                  "AutoDestroy": true,
                  "StopWhenOwnerDestroyed": true,
                  "LOD": "ESBAkEventLOD::LOD_Default",
                  "RTPC": [],
                  "DelayTime": 0.0,
                  "bCanReuseAkComponent": true
                },
                "EndSound": {
                  "AssetPathName": "/Game/WwiseAudio/Events/Default_Work_Unit/Stop_Elem_Fire_LOOP_E001_Weapon_Fire.Stop_Elem_Fire_LOOP_E001_Weapon_Fire",
                  "SubPathString": ""
                },
                "EndSoundParam": {
                  "Event": null,
                  "Switch": [],
                  "AttachName": "None",
                  "AutoDestroy": true,
                  "StopWhenOwnerDestroyed": true,
                  "LOD": "ESBAkEventLOD::LOD_Default",
                  "RTPC": [],
                  "DelayTime": 0.0,
                  "bCanReuseAkComponent": true
                },
                "EffectTarget": "EffectTarget_WeaponMesh_R",
                "ParticleScale": 3.0,
                "LocationOffset": {
                  "X": 0.0,
                  "Y": 0.0,
                  "Z": 0.0
                },
                "RotationOffset": {
                  "Pitch": 0.0,
                  "Yaw": 0.0,
                  "Roll": 0.0
                },
                "bAttach": true,
                "bAbsoluteRotation": false,
                "bDetachWhenDeactivate": false,
                "bVisibleByHiddenSourceActor": false,
                "AttachPointName": "Center_J",
                "ActorParameterName": "None",
                "bOverrideLightingChannels": false,
                "OverrideLightingChannels": {
                  "bChannel0": true,
                  "bChannel1": false,
                  "bChannel2": false
                },
                "bOverrideElementType": false,
                "ElementType": "ESBAttribute::None",
                "VisibleType": "ESBEffectVisibleType::Battle_Production",
                "EffectType": "ESBEffectType::Default"
              }
            }
          ],
          "UnsheatheEffectList": []
        },
        "WeaponAsset2": {
          "WeaponBase": {
            "AssetPathName": "None",
            "SubPathString": ""
          },
          "Mesh": {
            "AssetPathName": "None",
            "SubPathString": ""
          },
          "ColorList": {
            "AssetPathName": "None",
            "SubPathString": ""
          },
          "MaterialSetList": [],
          "EnvironmentEffectList": [],
          "UnsheatheEffectList": []
        }
      },
      "WE02_01_05": {
        "IsTwinWeapon": false,
        "IsTwinWeaponAssetDiff": false,
        "WeaponAsset1": {
          "WeaponBase": {
            "AssetPathName": "/Game/Blueprints/Weapon/Base/BP_Weapon.BP_Weapon_C",
            "SubPathString": ""
          },
          "Mesh": {
            "AssetPathName": "/Game/Character/Weapon/WE/SK_CH_WE02_01_01/Model/SK_CH_WE02_01_01.SK_CH_WE02_01_01",
            "SubPathString": ""
          },
          "ColorList": {
            "AssetPathName": "None",
            "SubPathString": ""
          },
          "MaterialSetList": [],
          "EnvironmentEffectList": [],
          "UnsheatheEffectList": []
        },
        "WeaponAsset2": {
          "WeaponBase": {
            "AssetPathName": "None",
            "SubPathString": ""
          },
          "Mesh": {
            "AssetPathName": "None",
            "SubPathString": ""
          },
          "ColorList": {
            "AssetPathName": "None",
            "SubPathString": ""
          },
          "MaterialSetList": [],
          "EnvironmentEffectList": [],
          "UnsheatheEffectList": []
        }
      },
      "WE02_02_01": {
        "IsTwinWeapon": false,
        "IsTwinWeaponAssetDiff": false,
        "WeaponAsset1": {
          "WeaponBase": {
            "AssetPathName": "/Game/Blueprints/Weapon/Base/BP_Weapon.BP_Weapon_C",
            "SubPathString": ""
          },
          "Mesh": {
            "AssetPathName": "/Game/Character/Weapon/WE/SK_CH_WE02_02_01/Model/SK_CH_WE02_02_01.SK_CH_WE02_02_01",
            "SubPathString": ""
          },
          "ColorList": {
            "AssetPathName": "None",
            "SubPathString": ""
          },
          "MaterialSetList": [],
          "EnvironmentEffectList": [],
          "UnsheatheEffectList": []
        },
        "WeaponAsset2": {
          "WeaponBase": {
            "AssetPathName": "None",
            "SubPathString": ""
          },
          "Mesh": {
            "AssetPathName": "None",
            "SubPathString": ""
          },
          "ColorList": {
            "AssetPathName": "None",
            "SubPathString": ""
          },
          "MaterialSetList": [],
          "EnvironmentEffectList": [],
          "UnsheatheEffectList": []
        }
      },
      "WE02_02_03": {
        "IsTwinWeapon": false,
        "IsTwinWeaponAssetDiff": false,
        "WeaponAsset1": {
          "WeaponBase": {
            "AssetPathName": "/Game/Blueprints/Weapon/Base/BP_Weapon.BP_Weapon_C",
            "SubPathString": ""
          },
          "Mesh": {
            "AssetPathName": "/Game/Character/Weapon/WE/SK_CH_WE02_02_01/Model/SK_CH_WE02_02_01.SK_CH_WE02_02_01",
            "SubPathString": ""
          },
          "ColorList": {
            "AssetPathName": "None",
            "SubPathString": ""
          },
          "MaterialSetList": [
            {
              "AssetPathName": "/Game/Character/Weapon/WE/SK_CH_WE02_02_03/Material/MS_CH_WE02_02_03.MS_CH_WE02_02_03",
              "SubPathString": ""
            }
          ],
          "EnvironmentEffectList": [],
          "UnsheatheEffectList": []
        },
        "WeaponAsset2": {
          "WeaponBase": {
            "AssetPathName": "None",
            "SubPathString": ""
          },
          "Mesh": {
            "AssetPathName": "None",
            "SubPathString": ""
          },
          "ColorList": {
            "AssetPathName": "None",
            "SubPathString": ""
          },
          "MaterialSetList": [],
          "EnvironmentEffectList": [],
          "UnsheatheEffectList": []
        }
      },
      "WE04_03_01": {
        "IsTwinWeapon": false,
        "IsTwinWeaponAssetDiff": false,
        "WeaponAsset1": {
          "WeaponBase": {
            "AssetPathName": "/Game/Blueprints/Weapon/Enemy/WE04_Base.WE04_Base_C",
            "SubPathString": ""
          },
          "Mesh": {
            "AssetPathName": "/Game/Character/Weapon/WE/SK_CH_WE04_03_01/Model/SK_CH_WE04_03_01.SK_CH_WE04_03_01",
            "SubPathString": ""
          },
          "ColorList": {
            "AssetPathName": "None",
            "SubPathString": ""
          },
          "MaterialSetList": [],
          "EnvironmentEffectList": [
            {
              "Type": "EEnvironmentType::Unsheathe",
              "bIsPlay": true,
              "Effect": {
                "Particle": {
                  "AssetPathName": "None",
                  "SubPathString": ""
                },
                "NiagaraSystem": {
                  "AssetPathName": "None",
                  "SubPathString": ""
                },
                "EffectActor": {
                  "AssetPathName": "None",
                  "SubPathString": ""
                },
                "EffectActorList": [],
                "Sound": {
                  "AssetPathName": "None",
                  "SubPathString": ""
                },
                "SoundParam": {
                  "Event": null,
                  "Switch": [],
                  "AttachName": "None",
                  "AutoDestroy": true,
                  "StopWhenOwnerDestroyed": true,
                  "LOD": "ESBAkEventLOD::LOD_Default",
                  "RTPC": [],
                  "DelayTime": 0.0,
                  "bCanReuseAkComponent": true
                },
                "EndSound": {
                  "AssetPathName": "None",
                  "SubPathString": ""
                },
                "EndSoundParam": {
                  "Event": null,
                  "Switch": [],
                  "AttachName": "None",
                  "AutoDestroy": true,
                  "StopWhenOwnerDestroyed": true,
                  "LOD": "ESBAkEventLOD::LOD_Default",
                  "RTPC": [],
                  "DelayTime": 0.0,
                  "bCanReuseAkComponent": true
                },
                "EffectTarget": "EffectTarget_ActorRoot",
                "ParticleScale": 1.0,
                "LocationOffset": {
                  "X": 0.0,
                  "Y": 0.0,
                  "Z": 0.0
                },
                "RotationOffset": {
                  "Pitch": 0.0,
                  "Yaw": 0.0,
                  "Roll": 0.0
                },
                "bAttach": true,
                "bAbsoluteRotation": false,
                "bDetachWhenDeactivate": false,
                "bVisibleByHiddenSourceActor": false,
                "AttachPointName": "None",
                "ActorParameterName": "None",
                "bOverrideLightingChannels": false,
                "OverrideLightingChannels": {
                  "bChannel0": true,
                  "bChannel1": false,
                  "bChannel2": false
                },
                "bOverrideElementType": false,
                "ElementType": "ESBAttribute::None",
                "VisibleType": "ESBEffectVisibleType::Battle_Production",
                "EffectType": "ESBEffectType::Default"
              }
            }
          ],
          "UnsheatheEffectList": []
        },
        "WeaponAsset2": {
          "WeaponBase": {
            "AssetPathName": "None",
            "SubPathString": ""
          },
          "Mesh": {
            "AssetPathName": "None",
            "SubPathString": ""
          },
          "ColorList": {
            "AssetPathName": "None",
            "SubPathString": ""
          },
          "MaterialSetList": [],
          "EnvironmentEffectList": [],
          "UnsheatheEffectList": []
        }
      },
      "WE04_03_02": {
        "IsTwinWeapon": false,
        "IsTwinWeaponAssetDiff": false,
        "WeaponAsset1": {
          "WeaponBase": {
            "AssetPathName": "/Game/Blueprints/Weapon/Enemy/WE04_Base.WE04_Base_C",
            "SubPathString": ""
          },
          "Mesh": {
            "AssetPathName": "/Game/Character/Weapon/WE/SK_CH_WE04_03_02/Model/SK_CH_WE04_03_02.SK_CH_WE04_03_02",
            "SubPathString": ""
          },
          "ColorList": {
            "AssetPathName": "None",
            "SubPathString": ""
          },
          "MaterialSetList": [],
          "EnvironmentEffectList": [],
          "UnsheatheEffectList": []
        },
        "WeaponAsset2": {
          "WeaponBase": {
            "AssetPathName": "None",
            "SubPathString": ""
          },
          "Mesh": {
            "AssetPathName": "None",
            "SubPathString": ""
          },
          "ColorList": {
            "AssetPathName": "None",
            "SubPathString": ""
          },
          "MaterialSetList": [],
          "EnvironmentEffectList": [],
          "UnsheatheEffectList": []
        }
      },
      "WE04_03_03": {
        "IsTwinWeapon": false,
        "IsTwinWeaponAssetDiff": false,
        "WeaponAsset1": {
          "WeaponBase": {
            "AssetPathName": "/Game/Blueprints/Weapon/Enemy/WE04_Base.WE04_Base_C",
            "SubPathString": ""
          },
          "Mesh": {
            "AssetPathName": "/Game/Character/Weapon/WE/SK_CH_WE04_03_03/Model/SK_CH_WE04_03_03.SK_CH_WE04_03_03",
            "SubPathString": ""
          },
          "ColorList": {
            "AssetPathName": "None",
            "SubPathString": ""
          },
          "MaterialSetList": [],
          "EnvironmentEffectList": [],
          "UnsheatheEffectList": []
        },
        "WeaponAsset2": {
          "WeaponBase": {
            "AssetPathName": "None",
            "SubPathString": ""
          },
          "Mesh": {
            "AssetPathName": "None",
            "SubPathString": ""
          },
          "ColorList": {
            "AssetPathName": "None",
            "SubPathString": ""
          },
          "MaterialSetList": [],
          "EnvironmentEffectList": [],
          "UnsheatheEffectList": []
        }
      },
      "WE05_01_01": {
        "IsTwinWeapon": false,
        "IsTwinWeaponAssetDiff": false,
        "WeaponAsset1": {
          "WeaponBase": {
            "AssetPathName": "/Game/Blueprints/Weapon/Base/BP_Weapon_Shield.BP_Weapon_Shield_C",
            "SubPathString": ""
          },
          "Mesh": {
            "AssetPathName": "/Game/Character/Weapon/WE/SK_CH_WE05_01_01/Model/SK_CH_WE05_01_01.SK_CH_WE05_01_01",
            "SubPathString": ""
          },
          "ColorList": {
            "AssetPathName": "None",
            "SubPathString": ""
          },
          "MaterialSetList": [],
          "EnvironmentEffectList": [],
          "UnsheatheEffectList": []
        },
        "WeaponAsset2": {
          "WeaponBase": {
            "AssetPathName": "None",
            "SubPathString": ""
          },
          "Mesh": {
            "AssetPathName": "None",
            "SubPathString": ""
          },
          "ColorList": {
            "AssetPathName": "None",
            "SubPathString": ""
          },
          "MaterialSetList": [],
          "EnvironmentEffectList": [],
          "UnsheatheEffectList": []
        }
      },
      "WE05_01_02": {
        "IsTwinWeapon": false,
        "IsTwinWeaponAssetDiff": false,
        "WeaponAsset1": {
          "WeaponBase": {
            "AssetPathName": "/Game/Blueprints/Weapon/Base/BP_Weapon_Shield.BP_Weapon_Shield_C",
            "SubPathString": ""
          },
          "Mesh": {
            "AssetPathName": "/Game/Character/Weapon/WE/SK_CH_WE05_01_02/Model/SK_CH_WE05_01_02.SK_CH_WE05_01_02",
            "SubPathString": ""
          },
          "ColorList": {
            "AssetPathName": "None",
            "SubPathString": ""
          },
          "MaterialSetList": [],
          "EnvironmentEffectList": [],
          "UnsheatheEffectList": []
        },
        "WeaponAsset2": {
          "WeaponBase": {
            "AssetPathName": "None",
            "SubPathString": ""
          },
          "Mesh": {
            "AssetPathName": "None",
            "SubPathString": ""
          },
          "ColorList": {
            "AssetPathName": "None",
            "SubPathString": ""
          },
          "MaterialSetList": [],
          "EnvironmentEffectList": [],
          "UnsheatheEffectList": []
        }
      },
      "WE05_01_03": {
        "IsTwinWeapon": false,
        "IsTwinWeaponAssetDiff": false,
        "WeaponAsset1": {
          "WeaponBase": {
            "AssetPathName": "/Game/Blueprints/Weapon/Base/BP_Weapon_Shield.BP_Weapon_Shield_C",
            "SubPathString": ""
          },
          "Mesh": {
            "AssetPathName": "/Game/Character/Weapon/WE/SK_CH_WE05_01_03/Model/SK_CH_WE05_01_03.SK_CH_WE05_01_03",
            "SubPathString": ""
          },
          "ColorList": {
            "AssetPathName": "None",
            "SubPathString": ""
          },
          "MaterialSetList": [],
          "EnvironmentEffectList": [],
          "UnsheatheEffectList": []
        },
        "WeaponAsset2": {
          "WeaponBase": {
            "AssetPathName": "None",
            "SubPathString": ""
          },
          "Mesh": {
            "AssetPathName": "None",
            "SubPathString": ""
          },
          "ColorList": {
            "AssetPathName": "None",
            "SubPathString": ""
          },
          "MaterialSetList": [],
          "EnvironmentEffectList": [],
          "UnsheatheEffectList": []
        }
      },
      "WE05_01_04": {
        "IsTwinWeapon": false,
        "IsTwinWeaponAssetDiff": false,
        "WeaponAsset1": {
          "WeaponBase": {
            "AssetPathName": "/Game/Blueprints/Weapon/Base/BP_Weapon_Shield.BP_Weapon_Shield_C",
            "SubPathString": ""
          },
          "Mesh": {
            "AssetPathName": "/Game/Character/Weapon/WE/SK_CH_WE05_01_04/Model/SK_CH_WE05_01_04.SK_CH_WE05_01_04",
            "SubPathString": ""
          },
          "ColorList": {
            "AssetPathName": "None",
            "SubPathString": ""
          },
          "MaterialSetList": [],
          "EnvironmentEffectList": [],
          "UnsheatheEffectList": []
        },
        "WeaponAsset2": {
          "WeaponBase": {
            "AssetPathName": "None",
            "SubPathString": ""
          },
          "Mesh": {
            "AssetPathName": "None",
            "SubPathString": ""
          },
          "ColorList": {
            "AssetPathName": "None",
            "SubPathString": ""
          },
          "MaterialSetList": [],
          "EnvironmentEffectList": [],
          "UnsheatheEffectList": []
        }
      },
      "WE05_01_05": {
        "IsTwinWeapon": false,
        "IsTwinWeaponAssetDiff": false,
        "WeaponAsset1": {
          "WeaponBase": {
            "AssetPathName": "/Game/Blueprints/Weapon/Base/BP_Weapon_Shield.BP_Weapon_Shield_C",
            "SubPathString": ""
          },
          "Mesh": {
            "AssetPathName": "/Game/Character/Weapon/WE/SK_CH_WE05_01_05/Model/SK_CH_WE05_01_05.SK_CH_WE05_01_05",
            "SubPathString": ""
          },
          "ColorList": {
            "AssetPathName": "None",
            "SubPathString": ""
          },
          "MaterialSetList": [],
          "EnvironmentEffectList": [],
          "UnsheatheEffectList": []
        },
        "WeaponAsset2": {
          "WeaponBase": {
            "AssetPathName": "None",
            "SubPathString": ""
          },
          "Mesh": {
            "AssetPathName": "None",
            "SubPathString": ""
          },
          "ColorList": {
            "AssetPathName": "None",
            "SubPathString": ""
          },
          "MaterialSetList": [],
          "EnvironmentEffectList": [],
          "UnsheatheEffectList": []
        }
      },
      "WE05_01_06": {
        "IsTwinWeapon": false,
        "IsTwinWeaponAssetDiff": false,
        "WeaponAsset1": {
          "WeaponBase": {
            "AssetPathName": "/Game/Blueprints/Weapon/Base/BP_Weapon_Shield.BP_Weapon_Shield_C",
            "SubPathString": ""
          },
          "Mesh": {
            "AssetPathName": "/Game/Character/Weapon/WE/SK_CH_WE05_01_06/Model/SK_CH_WE05_01_06.SK_CH_WE05_01_06",
            "SubPathString": ""
          },
          "ColorList": {
            "AssetPathName": "None",
            "SubPathString": ""
          },
          "MaterialSetList": [],
          "EnvironmentEffectList": [],
          "UnsheatheEffectList": []
        },
        "WeaponAsset2": {
          "WeaponBase": {
            "AssetPathName": "None",
            "SubPathString": ""
          },
          "Mesh": {
            "AssetPathName": "None",
            "SubPathString": ""
          },
          "ColorList": {
            "AssetPathName": "None",
            "SubPathString": ""
          },
          "MaterialSetList": [],
          "EnvironmentEffectList": [],
          "UnsheatheEffectList": []
        }
      },
      "WE05_01_07": {
        "IsTwinWeapon": false,
        "IsTwinWeaponAssetDiff": false,
        "WeaponAsset1": {
          "WeaponBase": {
            "AssetPathName": "/Game/Blueprints/Weapon/Base/BP_Weapon_Shield.BP_Weapon_Shield_C",
            "SubPathString": ""
          },
          "Mesh": {
            "AssetPathName": "/Game/Character/Weapon/WE/SK_CH_WE05_01_07/Model/SK_CH_WE05_01_07.SK_CH_WE05_01_07",
            "SubPathString": ""
          },
          "ColorList": {
            "AssetPathName": "None",
            "SubPathString": ""
          },
          "MaterialSetList": [],
          "EnvironmentEffectList": [],
          "UnsheatheEffectList": []
        },
        "WeaponAsset2": {
          "WeaponBase": {
            "AssetPathName": "None",
            "SubPathString": ""
          },
          "Mesh": {
            "AssetPathName": "None",
            "SubPathString": ""
          },
          "ColorList": {
            "AssetPathName": "None",
            "SubPathString": ""
          },
          "MaterialSetList": [],
          "EnvironmentEffectList": [],
          "UnsheatheEffectList": []
        }
      },
      "WE05_01_08": {
        "IsTwinWeapon": false,
        "IsTwinWeaponAssetDiff": false,
        "WeaponAsset1": {
          "WeaponBase": {
            "AssetPathName": "/Game/Blueprints/Weapon/Base/BP_Weapon_Shield.BP_Weapon_Shield_C",
            "SubPathString": ""
          },
          "Mesh": {
            "AssetPathName": "/Game/Character/Weapon/WE/SK_CH_WE05_01_07/Model/SK_CH_WE05_01_07.SK_CH_WE05_01_07",
            "SubPathString": ""
          },
          "ColorList": {
            "AssetPathName": "None",
            "SubPathString": ""
          },
          "MaterialSetList": [
            {
              "AssetPathName": "/Game/Character/Weapon/WE/SK_CH_WE05_01_07_02/Material/MS_CH_WE05_01_07_02.MS_CH_WE05_01_07_02",
              "SubPathString": ""
            }
          ],
          "EnvironmentEffectList": [],
          "UnsheatheEffectList": []
        },
        "WeaponAsset2": {
          "WeaponBase": {
            "AssetPathName": "None",
            "SubPathString": ""
          },
          "Mesh": {
            "AssetPathName": "None",
            "SubPathString": ""
          },
          "ColorList": {
            "AssetPathName": "None",
            "SubPathString": ""
          },
          "MaterialSetList": [],
          "EnvironmentEffectList": [],
          "UnsheatheEffectList": []
        }
      },
      "WE06_01_01": {
        "IsTwinWeapon": false,
        "IsTwinWeaponAssetDiff": false,
        "WeaponAsset1": {
          "WeaponBase": {
            "AssetPathName": "/Game/Blueprints/Weapon/Enemy/WE06_Base.WE06_Base_C",
            "SubPathString": ""
          },
          "Mesh": {
            "AssetPathName": "/Game/Character/Weapon/WE/SK_CH_WE06_01_01/Model/SK_CH_WE06_01_01.SK_CH_WE06_01_01",
            "SubPathString": ""
          },
          "ColorList": {
            "AssetPathName": "None",
            "SubPathString": ""
          },
          "MaterialSetList": [],
          "EnvironmentEffectList": [],
          "UnsheatheEffectList": []
        },
        "WeaponAsset2": {
          "WeaponBase": {
            "AssetPathName": "None",
            "SubPathString": ""
          },
          "Mesh": {
            "AssetPathName": "None",
            "SubPathString": ""
          },
          "ColorList": {
            "AssetPathName": "None",
            "SubPathString": ""
          },
          "MaterialSetList": [],
          "EnvironmentEffectList": [],
          "UnsheatheEffectList": []
        }
      },
      "WE06_01_02": {
        "IsTwinWeapon": false,
        "IsTwinWeaponAssetDiff": false,
        "WeaponAsset1": {
          "WeaponBase": {
            "AssetPathName": "/Game/Blueprints/Weapon/Enemy/WE06_Base.WE06_Base_C",
            "SubPathString": ""
          },
          "Mesh": {
            "AssetPathName": "/Game/Character/Weapon/WE/SK_CH_WE06_01_02/Model/SK_CH_WE06_01_02.SK_CH_WE06_01_02",
            "SubPathString": ""
          },
          "ColorList": {
            "AssetPathName": "None",
            "SubPathString": ""
          },
          "MaterialSetList": [],
          "EnvironmentEffectList": [],
          "UnsheatheEffectList": []
        },
        "WeaponAsset2": {
          "WeaponBase": {
            "AssetPathName": "None",
            "SubPathString": ""
          },
          "Mesh": {
            "AssetPathName": "None",
            "SubPathString": ""
          },
          "ColorList": {
            "AssetPathName": "None",
            "SubPathString": ""
          },
          "MaterialSetList": [],
          "EnvironmentEffectList": [],
          "UnsheatheEffectList": []
        }
      },
      "WE08_01_01": {
        "IsTwinWeapon": false,
        "IsTwinWeaponAssetDiff": false,
        "WeaponAsset1": {
          "WeaponBase": {
            "AssetPathName": "/Game/Blueprints/Weapon/Base/BP_Weapon.BP_Weapon_C",
            "SubPathString": ""
          },
          "Mesh": {
            "AssetPathName": "/Game/Character/Weapon/WE/SK_CH_WE08_01_01/Model/SK_CH_WE08_01_01.SK_CH_WE08_01_01",
            "SubPathString": ""
          },
          "ColorList": {
            "AssetPathName": "None",
            "SubPathString": ""
          },
          "MaterialSetList": [],
          "EnvironmentEffectList": [],
          "UnsheatheEffectList": []
        },
        "WeaponAsset2": {
          "WeaponBase": {
            "AssetPathName": "None",
            "SubPathString": ""
          },
          "Mesh": {
            "AssetPathName": "None",
            "SubPathString": ""
          },
          "ColorList": {
            "AssetPathName": "None",
            "SubPathString": ""
          },
          "MaterialSetList": [],
          "EnvironmentEffectList": [],
          "UnsheatheEffectList": []
        }
      },
      "WE08_01_02": {
        "IsTwinWeapon": false,
        "IsTwinWeaponAssetDiff": false,
        "WeaponAsset1": {
          "WeaponBase": {
            "AssetPathName": "/Game/Blueprints/Weapon/Base/BP_Weapon.BP_Weapon_C",
            "SubPathString": ""
          },
          "Mesh": {
            "AssetPathName": "/Game/Character/Weapon/WE/SK_CH_WE08_01_02/Model/SK_CH_WE08_01_02.SK_CH_WE08_01_02",
            "SubPathString": ""
          },
          "ColorList": {
            "AssetPathName": "None",
            "SubPathString": ""
          },
          "MaterialSetList": [],
          "EnvironmentEffectList": [],
          "UnsheatheEffectList": []
        },
        "WeaponAsset2": {
          "WeaponBase": {
            "AssetPathName": "None",
            "SubPathString": ""
          },
          "Mesh": {
            "AssetPathName": "None",
            "SubPathString": ""
          },
          "ColorList": {
            "AssetPathName": "None",
            "SubPathString": ""
          },
          "MaterialSetList": [],
          "EnvironmentEffectList": [],
          "UnsheatheEffectList": []
        }
      },
      "WE09_01_02": {
        "IsTwinWeapon": false,
        "IsTwinWeaponAssetDiff": false,
        "WeaponAsset1": {
          "WeaponBase": {
            "AssetPathName": "/Game/Blueprints/Weapon/Enemy/Old/WE09_01_02.WE09_01_02_C",
            "SubPathString": ""
          },
          "Mesh": {
            "AssetPathName": "None",
            "SubPathString": ""
          },
          "ColorList": {
            "AssetPathName": "None",
            "SubPathString": ""
          },
          "MaterialSetList": [],
          "EnvironmentEffectList": [],
          "UnsheatheEffectList": []
        },
        "WeaponAsset2": {
          "WeaponBase": {
            "AssetPathName": "None",
            "SubPathString": ""
          },
          "Mesh": {
            "AssetPathName": "None",
            "SubPathString": ""
          },
          "ColorList": {
            "AssetPathName": "None",
            "SubPathString": ""
          },
          "MaterialSetList": [],
          "EnvironmentEffectList": [],
          "UnsheatheEffectList": []
        }
      },
      "WE99_99_99": {
        "IsTwinWeapon": false,
        "IsTwinWeaponAssetDiff": false,
        "WeaponAsset1": {
          "WeaponBase": {
            "AssetPathName": "/Game/Blueprints/Weapon/Base/BP_Weapon_Shield.BP_Weapon_Shield_C",
            "SubPathString": ""
          },
          "Mesh": {
            "AssetPathName": "None",
            "SubPathString": ""
          },
          "ColorList": {
            "AssetPathName": "None",
            "SubPathString": ""
          },
          "MaterialSetList": [],
          "EnvironmentEffectList": [],
          "UnsheatheEffectList": []
        },
        "WeaponAsset2": {
          "WeaponBase": {
            "AssetPathName": "None",
            "SubPathString": ""
          },
          "Mesh": {
            "AssetPathName": "None",
            "SubPathString": ""
          },
          "ColorList": {
            "AssetPathName": "None",
            "SubPathString": ""
          },
          "MaterialSetList": [],
          "EnvironmentEffectList": [],
          "UnsheatheEffectList": []
        }
      },
      "WE10_01_01": {
        "IsTwinWeapon": false,
        "IsTwinWeaponAssetDiff": false,
        "WeaponAsset1": {
          "WeaponBase": {
            "AssetPathName": "/Game/Blueprints/Weapon/Base/BP_Weapon.BP_Weapon_C",
            "SubPathString": ""
          },
          "Mesh": {
            "AssetPathName": "/Game/Character/Weapon/WE/SK_CH_WE10_01_01/Model/SK_CH_WE10_01_01.SK_CH_WE10_01_01",
            "SubPathString": ""
          },
          "ColorList": {
            "AssetPathName": "None",
            "SubPathString": ""
          },
          "MaterialSetList": [],
          "EnvironmentEffectList": [],
          "UnsheatheEffectList": []
        },
        "WeaponAsset2": {
          "WeaponBase": {
            "AssetPathName": "None",
            "SubPathString": ""
          },
          "Mesh": {
            "AssetPathName": "None",
            "SubPathString": ""
          },
          "ColorList": {
            "AssetPathName": "None",
            "SubPathString": ""
          },
          "MaterialSetList": [],
          "EnvironmentEffectList": [],
          "UnsheatheEffectList": []
        }
      },
      "WE10_01_02": {
        "IsTwinWeapon": false,
        "IsTwinWeaponAssetDiff": false,
        "WeaponAsset1": {
          "WeaponBase": {
            "AssetPathName": "/Game/Blueprints/Weapon/Base/BP_Weapon.BP_Weapon_C",
            "SubPathString": ""
          },
          "Mesh": {
            "AssetPathName": "/Game/Character/Weapon/WE/SK_CH_WE10_01_02/Model/SK_CH_WE10_01_02.SK_CH_WE10_01_02",
            "SubPathString": ""
          },
          "ColorList": {
            "AssetPathName": "None",
            "SubPathString": ""
          },
          "MaterialSetList": [],
          "EnvironmentEffectList": [],
          "UnsheatheEffectList": []
        },
        "WeaponAsset2": {
          "WeaponBase": {
            "AssetPathName": "None",
            "SubPathString": ""
          },
          "Mesh": {
            "AssetPathName": "None",
            "SubPathString": ""
          },
          "ColorList": {
            "AssetPathName": "None",
            "SubPathString": ""
          },
          "MaterialSetList": [],
          "EnvironmentEffectList": [],
          "UnsheatheEffectList": []
        }
      },
      "WP05_G_03_KAK": {
        "IsTwinWeapon": false,
        "IsTwinWeaponAssetDiff": false,
        "WeaponAsset1": {
          "WeaponBase": {
            "AssetPathName": "/Game/Blueprints/Weapon/Enemy/WP05_KAK.WP05_KAK_C",
            "SubPathString": ""
          },
          "Mesh": {
            "AssetPathName": "/Game/Character/Weapon/WP/SK_CH_WP05_G_03/Model/SK_CH_WP05_G_03.SK_CH_WP05_G_03",
            "SubPathString": ""
          },
          "ColorList": {
            "AssetPathName": "None",
            "SubPathString": ""
          },
          "MaterialSetList": [],
          "EnvironmentEffectList": [],
          "UnsheatheEffectList": []
        },
        "WeaponAsset2": {
          "WeaponBase": {
            "AssetPathName": "None",
            "SubPathString": ""
          },
          "Mesh": {
            "AssetPathName": "None",
            "SubPathString": ""
          },
          "ColorList": {
            "AssetPathName": "None",
            "SubPathString": ""
          },
          "MaterialSetList": [],
          "EnvironmentEffectList": [],
          "UnsheatheEffectList": []
        }
      },
      "WP16_A_02": {
        "IsTwinWeapon": false,
        "IsTwinWeaponAssetDiff": false,
        "WeaponAsset1": {
          "WeaponBase": {
            "AssetPathName": "/Game/Blueprints/Weapon/Base/BP_Weapon_HandSword.BP_Weapon_HandSword_C",
            "SubPathString": ""
          },
          "Mesh": {
            "AssetPathName": "/Game/Character/Weapon/WP/SK_CH_WP16_A_02/Model/SK_CH_WP16_A_02.SK_CH_WP16_A_02",
            "SubPathString": ""
          },
          "ColorList": {
            "AssetPathName": "None",
            "SubPathString": ""
          },
          "MaterialSetList": [],
          "EnvironmentEffectList": [],
          "UnsheatheEffectList": []
        },
        "WeaponAsset2": {
          "WeaponBase": {
            "AssetPathName": "None",
            "SubPathString": ""
          },
          "Mesh": {
            "AssetPathName": "None",
            "SubPathString": ""
          },
          "ColorList": {
            "AssetPathName": "None",
            "SubPathString": ""
          },
          "MaterialSetList": [],
          "EnvironmentEffectList": [],
          "UnsheatheEffectList": []
        }
      },
      "WP11_H_01_02": {
        "IsTwinWeapon": false,
        "IsTwinWeaponAssetDiff": false,
        "WeaponAsset1": {
          "WeaponBase": {
            "AssetPathName": "/Game/Blueprints/Weapon/Base/BP_Weapon_HandSword.BP_Weapon_HandSword_C",
            "SubPathString": ""
          },
          "Mesh": {
            "AssetPathName": "/Game/Character/Weapon/WP/SK_CH_WP11_H_01/Model/SK_CH_WP11_H_01_02.SK_CH_WP11_H_01_02",
            "SubPathString": ""
          },
          "ColorList": {
            "AssetPathName": "None",
            "SubPathString": ""
          },
          "MaterialSetList": [],
          "EnvironmentEffectList": [],
          "UnsheatheEffectList": []
        },
        "WeaponAsset2": {
          "WeaponBase": {
            "AssetPathName": "None",
            "SubPathString": ""
          },
          "Mesh": {
            "AssetPathName": "None",
            "SubPathString": ""
          },
          "ColorList": {
            "AssetPathName": "None",
            "SubPathString": ""
          },
          "MaterialSetList": [],
          "EnvironmentEffectList": [],
          "UnsheatheEffectList": []
        }
      }
    }
  }
]