[
  {
    "Type": "CurveVector",
    "Name": "MoveCurve_FFF_UkemiFront",
    "Class": "UScriptClass'CurveVector'",
    "FloatCurves": [
      {
        "Keys": [
          {
            "InterpMode": "RCIM_Cubic",
            "TangentMode": "RCTM_User",
            "TangentWeightMode": "RCTWM_WeightedNone",
            "Time": 0.0,
            "Value": 0.0,
            "ArriveTangent": 9.956991,
            "ArriveTangentWeight": 0.0,
            "LeaveTangent": 9.956991,
            "LeaveTangentWeight": 0.0
          },
          {
            "InterpMode": "RCIM_Cubic",
            "TangentMode": "RCTM_User",
            "TangentWeightMode": "RCTWM_WeightedNone",
            "Time": 0.02,
            "Value": 0.0,
            "ArriveTangent": 1.293247,
            "ArriveTangentWeight": 0.0,
            "LeaveTangent": 1.293247,
            "LeaveTangentWeight": 0.0
          },
          {
            "InterpMode": "RCIM_Cubic",
            "TangentMode": "RCTM_User",
            "TangentWeightMode": "RCTWM_WeightedNone",
            "Time": 0.45,
            "Value": 400.0,
            "ArriveTangent": -1.752461,
            "ArriveTangentWeight": 0.0,
            "LeaveTangent": -1.752461,
            "LeaveTangentWeight": 0.0
          },
          {
            "InterpMode": "RCIM_Cubic",
            "TangentMode": "RCTM_User",
            "TangentWeightMode": "RCTWM_WeightedNone",
            "Time": 0.6,
            "Value": 400.0,
            "ArriveTangent": 6.2932315,
            "ArriveTangentWeight": 0.0,
            "LeaveTangent": 6.2932315,
            "LeaveTangentWeight": 0.0
          }
        ],
        "DefaultValue": 3.4028235E+38,
        "PreInfinityExtrap": "RCCE_Constant",
        "PostInfinityExtrap": "RCCE_Constant"
      },
      null,
      null
    ]
  }
]