[
  {
    "Type": "CharaPartsColorWeaponList",
    "Name": "CL_CH_WP06_BE_01",
    "Class": "UScriptClass'CharaPartsColorWeaponList'",
    "Properties": {
      "ColorList": [
        {
          "EmissiveColor1": {
            "R": 1.0,
            "G": 0.944687,
            "B": 0.892754,
            "A": 1.0,
            "Hex": "FFFFF9F3"
          },
          "EmissiveColor2": {
            "R": 0.95157,
            "G": 1.0,
            "B": 0.943905,
            "A": 1.0,
            "Hex": "FFFAFFF9"
          },
          "IsValid": false,
          "Name": "Default",
          "BaseColor1": {
            "R": 1.0,
            "G": 1.0,
            "B": 1.0,
            "A": 1.0,
            "Hex": "FFFFFFFF"
          },
          "BaseColor2": {
            "R": 1.0,
            "G": 1.0,
            "B": 1.0,
            "A": 1.0,
            "Hex": "FFFFFFFF"
          },
          "BaseColor3": {
            "R": 1.0,
            "G": 1.0,
            "B": 1.0,
            "A": 1.0,
            "Hex": "FFFFFFFF"
          },
          "BaseColor4": {
            "R": 1.0,
            "G": 1.0,
            "B": 1.0,
            "A": 1.0,
            "Hex": "FFFFFFFF"
          }
        },
        {
          "EmissiveColor1": {
            "R": 1.2,
            "G": 0.293655,
            "B": 0.547967,
            "A": 1.0,
            "Hex": "FFFF94C4"
          },
          "EmissiveColor2": {
            "R": 1.0,
            "G": 0.445201,
            "B": 0.351533,
            "A": 1.0,
            "Hex": "FFFFB2A0"
          },
          "IsValid": true,
          "Name": "Color1",
          "BaseColor1": {
            "R": 0.897,
            "G": 0.238819,
            "B": 0.207658,
            "A": 1.0,
            "Hex": "FFF4867E"
          },
          "BaseColor2": {
            "R": 0.338542,
            "G": 0.080913,
            "B": 0.038255,
            "A": 1.0,
            "Hex": "FF9D5037"
          },
          "BaseColor3": {
            "R": 0.787,
            "G": 0.170189,
            "B": 0.137725,
            "A": 1.0,
            "Hex": "FFE67368"
          },
          "BaseColor4": {
            "R": 0.75,
            "G": 0.17625,
            "B": 0.1125,
            "A": 1.0,
            "Hex": "FFE1745E"
          }
        },
        {
          "EmissiveColor1": {
            "R": 0.06,
            "G": 0.918882,
            "B": 1.2,
            "A": 1.0,
            "Hex": "FF45F6FF"
          },
          "EmissiveColor2": {
            "R": 0.417885,
            "G": 0.64448,
            "B": 0.799103,
            "A": 1.0,
            "Hex": "FFADD2E7"
          },
          "IsValid": true,
          "Name": "Color2",
          "BaseColor1": {
            "R": 0.1415,
            "G": 0.2371,
            "B": 0.5,
            "A": 1.0,
            "Hex": "FF6986BC"
          },
          "BaseColor2": {
            "R": 0.044814,
            "G": 0.113599,
            "B": 0.291,
            "A": 1.0,
            "Hex": "FF3B5F93"
          },
          "BaseColor3": {
            "R": 0.15409,
            "G": 0.1463,
            "B": 0.38,
            "A": 1.0,
            "Hex": "FF6D6BA6"
          },
          "BaseColor4": {
            "R": 0.414716,
            "G": 0.643487,
            "B": 0.796,
            "A": 1.0,
            "Hex": "FFADD2E7"
          }
        },
        {
          "EmissiveColor1": {
            "R": 1.2,
            "G": 1.02,
            "B": 0.0,
            "A": 1.0,
            "Hex": "FFFFFF00"
          },
          "EmissiveColor2": {
            "R": 0.83077,
            "G": 0.775822,
            "B": 0.318547,
            "A": 1.0,
            "Hex": "FFEBE499"
          },
          "IsValid": true,
          "Name": "Color3",
          "BaseColor1": {
            "R": 0.6,
            "G": 0.46783,
            "B": 0.24,
            "A": 1.0,
            "Hex": "FFCCB686"
          },
          "BaseColor2": {
            "R": 0.12,
            "G": 0.138071,
            "B": 0.2,
            "A": 1.0,
            "Hex": "FF61687C"
          },
          "BaseColor3": {
            "R": 0.826,
            "G": 0.773222,
            "B": 0.316255,
            "A": 1.0,
            "Hex": "FFEBE499"
          },
          "BaseColor4": {
            "R": 0.695,
            "G": 0.634188,
            "B": 0.17375,
            "A": 1.0,
            "Hex": "FFDAD174"
          }
        },
        {
          "EmissiveColor1": {
            "R": 1.2,
            "G": 0.212,
            "B": 0.06,
            "A": 1.0,
            "Hex": "FFFF7F45"
          },
          "EmissiveColor2": {
            "R": 1.0,
            "G": 0.371459,
            "B": 0.029,
            "A": 1.0,
            "Hex": "FFFFA42F"
          },
          "IsValid": true,
          "Name": "Color4",
          "BaseColor1": {
            "R": 0.3,
            "G": 0.204,
            "B": 0.18,
            "A": 1.0,
            "Hex": "FF957D76"
          },
          "BaseColor2": {
            "R": 0.13875,
            "G": 0.15,
            "B": 0.13875,
            "A": 1.0,
            "Hex": "FF686C68"
          },
          "BaseColor3": {
            "R": 0.22925,
            "G": 0.1925,
            "B": 0.35,
            "A": 1.0,
            "Hex": "FF8479A0"
          },
          "BaseColor4": {
            "R": 0.7,
            "G": 0.40815,
            "B": 0.21,
            "A": 1.0,
            "Hex": "FFDAAB7E"
          }
        },
        {
          "EmissiveColor1": {
            "R": 1.2,
            "G": 0.96472,
            "B": 0.3696,
            "A": 1.0,
            "Hex": "FFFFFBA4"
          },
          "EmissiveColor2": {
            "R": 0.8,
            "G": 0.554991,
            "B": 0.158663,
            "A": 1.0,
            "Hex": "FFE8C56F"
          },
          "IsValid": true,
          "Name": "Color5",
          "BaseColor1": {
            "R": 0.6,
            "G": 0.46783,
            "B": 0.24,
            "A": 1.0,
            "Hex": "FFCCB686"
          },
          "BaseColor2": {
            "R": 0.95,
            "G": 0.85035,
            "B": 0.8075,
            "A": 1.0,
            "Hex": "FFFAEEE8"
          },
          "BaseColor3": {
            "R": 0.12,
            "G": 0.138071,
            "B": 0.2,
            "A": 1.0,
            "Hex": "FF61687C"
          },
          "BaseColor4": {
            "R": 0.6,
            "G": 0.434788,
            "B": 0.15,
            "A": 1.0,
            "Hex": "FFCCB06C"
          }
        },
        {
          "EmissiveColor1": {
            "R": 0.981361,
            "G": 0.0,
            "B": 1.2,
            "A": 1.0,
            "Hex": "FFFD00FF"
          },
          "EmissiveColor2": {
            "R": 0.390972,
            "G": 0.075411,
            "B": 0.441,
            "A": 1.0,
            "Hex": "FFA84DB1"
          },
          "IsValid": true,
          "Name": "Color6",
          "BaseColor1": {
            "R": 0.220215,
            "G": 0.2125,
            "B": 0.25,
            "A": 1.0,
            "Hex": "FF817F89"
          },
          "BaseColor2": {
            "R": 0.0825,
            "G": 0.105,
            "B": 0.15,
            "A": 1.0,
            "Hex": "FF515B6C"
          },
          "BaseColor3": {
            "R": 0.258333,
            "G": 0.25,
            "B": 0.5,
            "A": 1.0,
            "Hex": "FF8B89BC"
          },
          "BaseColor4": {
            "R": 0.191668,
            "G": 0.15,
            "B": 0.25,
            "A": 1.0,
            "Hex": "FF796C89"
          }
        }
      ]
    }
  }
]