[
  {
    "Type": "SBTextTableAsset",
    "Name": "SQ101_125",
    "Class": "UScriptClass'SBTextTableAsset'",
    "Properties": {
      "TextTable": [
        {
          "Id": {
            "IdString": "0",
            "FallbackId": "None",
            "IdNumber": 0
          },
          "Text": "困った……あの石は、捨てるわけには……",
          "MetaData": [
            {
              "speaker_id": "Npc_Studs"
            },
            {
              "listener_id": "Npc_Studs"
            }
          ],
          "Version": {
            "Versions": []
          }
        },
        {
          "Id": {
            "IdString": "1",
            "FallbackId": "None",
            "IdNumber": 1
          },
          "Text": "しかし、取りに行くには……危険だ",
          "MetaData": [
            {
              "speaker_id": "Npc_Studs"
            },
            {
              "listener_id": "Npc_Studs"
            }
          ],
          "Version": {
            "Versions": []
          }
        },
        {
          "Id": {
            "IdString": "2",
            "FallbackId": "None",
            "IdNumber": 2
          },
          "Text": "……引き受けてくれて……助かる……。\r\n俺一人では……どうにもならなさそうだ",
          "MetaData": [
            {
              "speaker_id": "Npc_Studs"
            },
            {
              "listener_id": "Player"
            }
          ],
          "Version": {
            "Versions": []
          }
        },
        {
          "Id": {
            "IdString": "3",
            "FallbackId": "None",
            "IdNumber": 3
          },
          "Text": "俺はスタッズ……。石を集める旅をしている。\r\n[蒐集家(しゅうしゅうか)]……とでもいうのか",
          "MetaData": [
            {
              "speaker_id": "Npc_Studs"
            },
            {
              "listener_id": "Player"
            }
          ],
          "Version": {
            "Versions": []
          }
        },
        {
          "Id": {
            "IdString": "4",
            "FallbackId": "None",
            "IdNumber": 4
          },
          "Text": "あちこちを旅して……\r\n価値のある石を……拾っている",
          "MetaData": [
            {
              "speaker_id": "Npc_Studs"
            },
            {
              "listener_id": "Player"
            }
          ],
          "Version": {
            "Versions": []
          }
        },
        {
          "Id": {
            "IdString": "5",
            "FallbackId": "None",
            "IdNumber": 5
          },
          "Text": "だが、ミンスターホルンに来る途中……\r\nモンスターに……襲われてな",
          "MetaData": [
            {
              "speaker_id": "Npc_Studs"
            },
            {
              "listener_id": "Player"
            }
          ],
          "Version": {
            "Versions": []
          }
        },
        {
          "Id": {
            "IdString": "6",
            "FallbackId": "None",
            "IdNumber": 6
          },
          "Text": "思わず……『価値ある石』を投げつけて……\r\n相手が怯んだ隙に……逃げてきてしまった",
          "MetaData": [
            {
              "speaker_id": "Npc_Studs"
            },
            {
              "listener_id": "Player"
            }
          ],
          "Version": {
            "Versions": []
          }
        },
        {
          "Id": {
            "IdString": "7",
            "FallbackId": "None",
            "IdNumber": 7
          },
          "Text": "あれは……良い石だった。\r\n長い旅路でも……屈指の掘り出し物だ",
          "MetaData": [
            {
              "speaker_id": "Npc_Studs"
            },
            {
              "listener_id": "Player"
            }
          ],
          "Version": {
            "Versions": []
          }
        },
        {
          "Id": {
            "IdString": "8",
            "FallbackId": "None",
            "IdNumber": 8
          },
          "Text": "もう一度拾いに行きたいが……\r\nまた襲われては……きりがない",
          "MetaData": [
            {
              "speaker_id": "Npc_Studs"
            },
            {
              "listener_id": "Player"
            }
          ],
          "Version": {
            "Versions": []
          }
        },
        {
          "Id": {
            "IdString": "9",
            "FallbackId": "None",
            "IdNumber": 9
          },
          "Text": "悪いが……代わりに……\r\n『価値ある石』を拾ってきてくれないか",
          "MetaData": [
            {
              "speaker_id": "Npc_Studs"
            },
            {
              "listener_id": "Player"
            }
          ],
          "Version": {
            "Versions": []
          }
        },
        {
          "Id": {
            "IdString": "10",
            "FallbackId": "None",
            "IdNumber": 10
          },
          "Text": "場所は……少し遠い……。\r\nマウントイマジンを使うと……楽だ",
          "MetaData": [
            {
              "speaker_id": "Npc_Studs"
            },
            {
              "listener_id": "Player"
            }
          ],
          "Version": {
            "Versions": []
          }
        },
        {
          "Id": {
            "IdString": "11",
            "FallbackId": "None",
            "IdNumber": 11
          },
          "Text": "マウントイマジン……分かるか？\r\n乗り物型のイマジンだ……",
          "MetaData": [
            {
              "speaker_id": "Npc_Studs"
            },
            {
              "listener_id": "Player"
            }
          ],
          "Version": {
            "Versions": []
          }
        },
        {
          "Id": {
            "IdString": "12",
            "FallbackId": "None",
            "IdNumber": 12
          },
          "Text": "使えば、徒歩より……ずっと速く移動できる。\r\nいつでも取り出せて……便利だ……",
          "MetaData": [
            {
              "speaker_id": "Npc_Studs"
            },
            {
              "listener_id": "Player"
            }
          ],
          "Version": {
            "Versions": []
          }
        },
        {
          "Id": {
            "IdString": "13",
            "FallbackId": "None",
            "IdNumber": 13
          },
          "Text": "冒険者には……きっと役に立つ。\r\n移動がとてもスムーズで……楽しくなる",
          "MetaData": [
            {
              "speaker_id": "Npc_Studs"
            },
            {
              "listener_id": "Player"
            }
          ],
          "Version": {
            "Versions": []
          }
        },
        {
          "Id": {
            "IdString": "14",
            "FallbackId": "None",
            "IdNumber": 14
          },
          "Text": "しかし、俺は……石のほうがいい",
          "MetaData": [
            {
              "speaker_id": "Npc_Studs"
            },
            {
              "listener_id": "Player"
            }
          ],
          "Version": {
            "Versions": []
          }
        },
        {
          "Id": {
            "IdString": "15",
            "FallbackId": "None",
            "IdNumber": 15
          },
          "Text": "あの石の魅力……何物にも代え難いものだった。\r\nもしかしたら……モンスターも気に入るかもしれない",
          "MetaData": [
            {
              "speaker_id": "Npc_Studs"
            },
            {
              "listener_id": "Player"
            }
          ],
          "Version": {
            "Versions": []
          }
        },
        {
          "Id": {
            "IdString": "16",
            "FallbackId": "None",
            "IdNumber": 16
          },
          "Text": "誰かが気づいて持ち去る前に……頼む",
          "MetaData": [
            {
              "speaker_id": "Npc_Studs"
            },
            {
              "listener_id": "Player"
            }
          ],
          "Version": {
            "Versions": []
          }
        },
        {
          "Id": {
            "IdString": "17",
            "FallbackId": "None",
            "IdNumber": 17
          },
          "Text": "地図を見てもらえば……\r\nだいたいの場所が……分かるだろう……",
          "MetaData": [
            {
              "speaker_id": "Npc_Studs"
            },
            {
              "listener_id": "Player"
            }
          ],
          "Version": {
            "Versions": []
          }
        },
        {
          "Id": {
            "IdString": "18",
            "FallbackId": "None",
            "IdNumber": 18
          },
          "Text": "普通の石じゃない……。\r\n『価値ある石』を……頼んだぞ",
          "MetaData": [
            {
              "speaker_id": "Npc_Studs"
            },
            {
              "listener_id": "Player"
            }
          ],
          "Version": {
            "Versions": []
          }
        },
        {
          "Id": {
            "IdString": "19",
            "FallbackId": "None",
            "IdNumber": 19
          },
          "Text": "首尾は……どうだ。\r\n『価値ある石』は……見つかったか",
          "MetaData": [
            {
              "speaker_id": "Npc_Studs"
            },
            {
              "listener_id": "Player"
            }
          ],
          "Version": {
            "Versions": []
          }
        },
        {
          "Id": {
            "IdString": "20",
            "FallbackId": "None",
            "IdNumber": 20
          },
          "Text": "少し……遠い場所になる……。\r\nマウントイマジンを使うのが……オススメだ……",
          "MetaData": [
            {
              "speaker_id": "Npc_Studs"
            },
            {
              "listener_id": "Player"
            }
          ],
          "Version": {
            "Versions": []
          }
        },
        {
          "Id": {
            "IdString": "21",
            "FallbackId": "None",
            "IdNumber": 21
          },
          "Text": "必死だったから……詳しい場所は覚えていないが、\r\n『<value type=\"locationName\" id=\"fld001_W\"/>』の……どこかだ",
          "MetaData": [
            {
              "speaker_id": "Npc_Studs"
            },
            {
              "listener_id": "Player"
            }
          ],
          "Version": {
            "Versions": []
          }
        },
        {
          "Id": {
            "IdString": "22",
            "FallbackId": "None",
            "IdNumber": 22
          },
          "Text": "よろしく……頼んだぞ",
          "MetaData": [
            {
              "speaker_id": "Npc_Studs"
            },
            {
              "listener_id": "Player"
            }
          ],
          "Version": {
            "Versions": []
          }
        },
        {
          "Id": {
            "IdString": "23",
            "FallbackId": "None",
            "IdNumber": 23
          },
          "Text": "これは……俺が投げた石だ。\r\n『価値ある石』だ……感謝する",
          "MetaData": [
            {
              "speaker_id": "Npc_Studs"
            },
            {
              "listener_id": "Player"
            }
          ],
          "Version": {
            "Versions": []
          }
        },
        {
          "Id": {
            "IdString": "24",
            "FallbackId": "None",
            "IdNumber": 24
          },
          "Text": "この石は……希少な鉱石でも宝石でもない。\r\n売ったところで……金にはならない",
          "MetaData": [
            {
              "speaker_id": "Npc_Studs"
            },
            {
              "listener_id": "Player"
            }
          ],
          "Version": {
            "Versions": []
          }
        },
        {
          "Id": {
            "IdString": "25",
            "FallbackId": "None",
            "IdNumber": 25
          },
          "Text": "だが、この石には……\r\n金に替えられない……価値がある",
          "MetaData": [
            {
              "speaker_id": "Npc_Studs"
            },
            {
              "listener_id": "Player"
            }
          ],
          "Version": {
            "Versions": []
          }
        },
        {
          "Id": {
            "IdString": "26",
            "FallbackId": "None",
            "IdNumber": 26
          },
          "Text": "このサイズ……表面の無骨なザラつき……。\r\n色合いも配置も……実に絶妙",
          "MetaData": [
            {
              "speaker_id": "Npc_Studs"
            },
            {
              "listener_id": "Player"
            }
          ],
          "Version": {
            "Versions": []
          }
        },
        {
          "Id": {
            "IdString": "27",
            "FallbackId": "None",
            "IdNumber": 27
          },
          "Text": "そして……分かるか。\r\nこの縦に入ったヒビ……これだ",
          "MetaData": [
            {
              "speaker_id": "Npc_Studs"
            },
            {
              "listener_id": "Player"
            }
          ],
          "Version": {
            "Versions": []
          }
        },
        {
          "Id": {
            "IdString": "28",
            "FallbackId": "None",
            "IdNumber": 28
          },
          "Text": "歴戦の肉体に入った……名誉の傷のようだろう",
          "MetaData": [
            {
              "speaker_id": "Npc_Studs"
            },
            {
              "listener_id": "Player"
            }
          ],
          "Version": {
            "Versions": []
          }
        },
        {
          "Id": {
            "IdString": "29",
            "FallbackId": "None",
            "IdNumber": 29
          },
          "Text": "…………",
          "MetaData": [
            {
              "speaker_id": "Npc_Studs"
            },
            {
              "listener_id": "Player"
            }
          ],
          "Version": {
            "Versions": []
          }
        },
        {
          "Id": {
            "IdString": "30",
            "FallbackId": "None",
            "IdNumber": 30
          },
          "Text": "……理解できないか？　……そうか。\r\n残念だが……それが普通の反応だ……",
          "MetaData": [
            {
              "speaker_id": "Npc_Studs"
            },
            {
              "listener_id": "Player"
            }
          ],
          "Version": {
            "Versions": []
          }
        },
        {
          "Id": {
            "IdString": "31",
            "FallbackId": "None",
            "IdNumber": 31
          },
          "Text": "大丈夫だ……慣れている。\r\nこれも[蒐集家(しゅうしゅうか)]の……宿命というやつだ",
          "MetaData": [
            {
              "speaker_id": "Npc_Studs"
            },
            {
              "listener_id": "Player"
            }
          ],
          "Version": {
            "Versions": []
          }
        },
        {
          "Id": {
            "IdString": "32",
            "FallbackId": "None",
            "IdNumber": 32
          },
          "Text": "そういえば……マウントイマジンは……\r\n使ってみたか？",
          "MetaData": [
            {
              "speaker_id": "Npc_Studs"
            },
            {
              "listener_id": "Player"
            }
          ],
          "Version": {
            "Versions": []
          }
        },
        {
          "Id": {
            "IdString": "33",
            "FallbackId": "None",
            "IdNumber": 33
          },
          "Text": "あれはフィールドだけじゃなく……\r\n街の中でも……乗れるものだ",
          "MetaData": [
            {
              "speaker_id": "Npc_Studs"
            },
            {
              "listener_id": "Player"
            }
          ],
          "Version": {
            "Versions": []
          }
        },
        {
          "Id": {
            "IdString": "34",
            "FallbackId": "None",
            "IdNumber": 34
          },
          "Text": "ダッシュすれば……かなりのスピードが……出る",
          "MetaData": [
            {
              "speaker_id": "Npc_Studs"
            },
            {
              "listener_id": "Player"
            }
          ],
          "Version": {
            "Versions": []
          }
        },
        {
          "Id": {
            "IdString": "35",
            "FallbackId": "None",
            "IdNumber": 35
          },
          "Text": "スタミナを消費するけどな……。\r\nそれも……時間が経てば回復する……はずだ",
          "MetaData": [
            {
              "speaker_id": "Npc_Studs"
            },
            {
              "listener_id": "Player"
            }
          ],
          "Version": {
            "Versions": []
          }
        },
        {
          "Id": {
            "IdString": "36",
            "FallbackId": "None",
            "IdNumber": 36
          },
          "Text": "遠出をする時は……歩くより……ずっと早い……",
          "MetaData": [
            {
              "speaker_id": "Npc_Studs"
            },
            {
              "listener_id": "Player"
            }
          ],
          "Version": {
            "Versions": []
          }
        },
        {
          "Id": {
            "IdString": "37",
            "FallbackId": "None",
            "IdNumber": 37
          },
          "Text": "俺は……石を見逃さないように……歩くが、\r\n冒険者には……マウントが便利だろう……",
          "MetaData": [
            {
              "speaker_id": "Npc_Studs"
            },
            {
              "listener_id": "Player"
            }
          ],
          "Version": {
            "Versions": []
          }
        },
        {
          "Id": {
            "IdString": "38",
            "FallbackId": "None",
            "IdNumber": 38
          },
          "Text": "いろいろな種類が……あると聞く。\r\nマウントイマジンの[蒐集家(しゅうしゅうか)]も……おもしろいかもな",
          "MetaData": [
            {
              "speaker_id": "Npc_Studs"
            },
            {
              "listener_id": "Player"
            }
          ],
          "Version": {
            "Versions": []
          }
        },
        {
          "Id": {
            "IdString": "39",
            "FallbackId": "None",
            "IdNumber": 39
          },
          "Text": "目立つマウントを使えば……\r\nきっと……人気者になれるぞ",
          "MetaData": [
            {
              "speaker_id": "Npc_Studs"
            },
            {
              "listener_id": "Player"
            }
          ],
          "Version": {
            "Versions": []
          }
        },
        {
          "Id": {
            "IdString": "40",
            "FallbackId": "None",
            "IdNumber": 40
          },
          "Text": "ふっ……石の蒐集家とは……違うな",
          "MetaData": [
            {
              "speaker_id": "Npc_Studs"
            },
            {
              "listener_id": "Player"
            }
          ],
          "Version": {
            "Versions": []
          }
        },
        {
          "Id": {
            "IdString": "41",
            "FallbackId": "None",
            "IdNumber": 41
          },
          "Text": "いいんだ……俺には、石があれば……。\r\nお前は……マウントや冒険を……楽しんでくれ",
          "MetaData": [
            {
              "speaker_id": "Npc_Studs"
            },
            {
              "listener_id": "Player"
            }
          ],
          "Version": {
            "Versions": []
          }
        },
        {
          "Id": {
            "IdString": "42",
            "FallbackId": "None",
            "IdNumber": 42
          },
          "Text": "石……ありがとうな。\r\nまた何かあったら……その時は頼む",
          "MetaData": [
            {
              "speaker_id": "Npc_Studs"
            },
            {
              "listener_id": "Player"
            }
          ],
          "Version": {
            "Versions": []
          }
        },
        {
          "Id": {
            "IdString": "43",
            "FallbackId": "None",
            "IdNumber": 43
          },
          "Text": "次の目的地は……どこだ？\r\n遠くなら……マウントを使うと良い",
          "MetaData": [
            {
              "speaker_id": "Npc_Studs"
            },
            {
              "listener_id": "Player"
            }
          ],
          "Version": {
            "Versions": []
          }
        },
        {
          "Id": {
            "IdString": "44",
            "FallbackId": "None",
            "IdNumber": 44
          },
          "Text": "使いこなしてやるほうが……\r\nマウントにとっても……良いことだろう",
          "MetaData": [
            {
              "speaker_id": "Npc_Studs"
            },
            {
              "listener_id": "Player"
            }
          ],
          "Version": {
            "Versions": []
          }
        }
      ]
    }
  }
]