[
  {
    "Type": "DataTable",
    "Name": "DT_EnemyPartsDB_E304",
    "Class": "UScriptClass'DataTable'",
    "Properties": {
      "RowStruct": {
        "ObjectName": "ScriptStruct'SBCharaPartsData'",
        "ObjectPath": "/Script/SkyBlue"
      }
    },
    "Rows": {
      "E304_00_body": {
        "bForceAddCharaCreateViewerList": false,
        "bRandomCreation": true,
        "PartsLocation": "ECharaPartsLocation::Body",
        "M000": {
          "ObjectName": "CharaPartsData'CP_CH_cmn_enm_C000_E304_00_00_bdu_000'",
          "ObjectPath": "BLUEPROTOCOL/Content/Character/CharaParts/Enemy/Body/CP_CH_cmn_enm_C000_E304_00_00_bdu_000.0"
        },
        "M100": null,
        "M200": null,
        "M300": null,
        "M400": null,
        "M500": null,
        "F000": null,
        "F100": null,
        "F200": null,
        "F300": null,
        "F400": null,
        "F500": null
      },
      "E304_00_01_body": {
        "bForceAddCharaCreateViewerList": false,
        "bRandomCreation": true,
        "PartsLocation": "ECharaPartsLocation::Body",
        "M000": {
          "ObjectName": "CharaPartsData'CP_CH_cmn_enm_C000_E304_00_00_bdu_000'",
          "ObjectPath": "BLUEPROTOCOL/Content/Character/CharaParts/Enemy/Body/CP_CH_cmn_enm_C000_E304_00_00_bdu_000.0"
        },
        "M100": null,
        "M200": null,
        "M300": null,
        "M400": null,
        "M500": null,
        "F000": null,
        "F100": null,
        "F200": null,
        "F300": null,
        "F400": null,
        "F500": null
      },
      "E304_00_02_body": {
        "bForceAddCharaCreateViewerList": false,
        "bRandomCreation": true,
        "PartsLocation": "ECharaPartsLocation::Body",
        "M000": {
          "ObjectName": "CharaPartsData'CP_CH_cmn_enm_C000_E304_00_00_bdu_000'",
          "ObjectPath": "BLUEPROTOCOL/Content/Character/CharaParts/Enemy/Body/CP_CH_cmn_enm_C000_E304_00_00_bdu_000.0"
        },
        "M100": null,
        "M200": null,
        "M300": null,
        "M400": null,
        "M500": null,
        "F000": null,
        "F100": null,
        "F200": null,
        "F300": null,
        "F400": null,
        "F500": null
      },
      "E304_01_body": {
        "bForceAddCharaCreateViewerList": false,
        "bRandomCreation": true,
        "PartsLocation": "ECharaPartsLocation::Body",
        "M000": {
          "ObjectName": "CharaPartsData'CP_CH_cmn_enm_C000_E304_01_00_bdu_000'",
          "ObjectPath": "BLUEPROTOCOL/Content/Character/CharaParts/Enemy/Body/CP_CH_cmn_enm_C000_E304_01_00_bdu_000.0"
        },
        "M100": null,
        "M200": null,
        "M300": null,
        "M400": null,
        "M500": null,
        "F000": null,
        "F100": null,
        "F200": null,
        "F300": null,
        "F400": null,
        "F500": null
      },
      "E304_01_01_body": {
        "bForceAddCharaCreateViewerList": false,
        "bRandomCreation": true,
        "PartsLocation": "ECharaPartsLocation::Body",
        "M000": {
          "ObjectName": "CharaPartsData'CP_CH_cmn_enm_C000_E304_01_00_bdu_000'",
          "ObjectPath": "BLUEPROTOCOL/Content/Character/CharaParts/Enemy/Body/CP_CH_cmn_enm_C000_E304_01_00_bdu_000.0"
        },
        "M100": null,
        "M200": null,
        "M300": null,
        "M400": null,
        "M500": null,
        "F000": null,
        "F100": null,
        "F200": null,
        "F300": null,
        "F400": null,
        "F500": null
      },
      "E304_02_body": {
        "bForceAddCharaCreateViewerList": false,
        "bRandomCreation": true,
        "PartsLocation": "ECharaPartsLocation::Body",
        "M000": {
          "ObjectName": "CharaPartsData'CP_CH_cmn_enm_C000_E304_02_00_bdu_000'",
          "ObjectPath": "BLUEPROTOCOL/Content/Character/CharaParts/Enemy/Body/CP_CH_cmn_enm_C000_E304_02_00_bdu_000.0"
        },
        "M100": null,
        "M200": null,
        "M300": null,
        "M400": null,
        "M500": null,
        "F000": null,
        "F100": null,
        "F200": null,
        "F300": null,
        "F400": null,
        "F500": null
      },
      "E304_02_01_body": {
        "bForceAddCharaCreateViewerList": false,
        "bRandomCreation": true,
        "PartsLocation": "ECharaPartsLocation::Body",
        "M000": {
          "ObjectName": "CharaPartsData'CP_CH_cmn_enm_C000_E304_02_00_bdu_000'",
          "ObjectPath": "BLUEPROTOCOL/Content/Character/CharaParts/Enemy/Body/CP_CH_cmn_enm_C000_E304_02_00_bdu_000.0"
        },
        "M100": null,
        "M200": null,
        "M300": null,
        "M400": null,
        "M500": null,
        "F000": null,
        "F100": null,
        "F200": null,
        "F300": null,
        "F400": null,
        "F500": null
      },
      "E304_03_body": {
        "bForceAddCharaCreateViewerList": false,
        "bRandomCreation": true,
        "PartsLocation": "ECharaPartsLocation::Body",
        "M000": {
          "ObjectName": "CharaPartsData'CP_CH_cmn_enm_C000_E304_03_00_bdu_000'",
          "ObjectPath": "BLUEPROTOCOL/Content/Character/CharaParts/Enemy/Body/CP_CH_cmn_enm_C000_E304_03_00_bdu_000.0"
        },
        "M100": null,
        "M200": null,
        "M300": null,
        "M400": null,
        "M500": null,
        "F000": null,
        "F100": null,
        "F200": null,
        "F300": null,
        "F400": null,
        "F500": null
      }
    }
  }
]